Workbook

Sheet Planilha1
A1: Meta | B1: 82 | C1: 64 | D1: 48 | E1: 42
B3: =SUM(B6:B104) -> 82 | C3: =SUM(C6:C104) -> 64 | D3: =SUM(D6:D104) -> 48 | E3: =SUM(E6:E104) -> 42 | F3: =SUM(F6:F104) -> 52 | G3: =SUM(G6:G104) -> 48 | H3: =SUM(H6:H104) -> 36 | I3: =SUM(I6:I104) -> 31 | ... K3: =SUM(K6:K104) -> 24
A5: ID | B5: A | C5: B | D5: C | E5: D | F5: A∩B | G5: A∩C | H5: A∩D | I5: B∩C | J5: B∩D | K5: C∩D | M5: Alias das categorias | N5: Descrição de cada categoria
A6: =ROW()-4 -> 2 | B6: =INT((ROW()-4)*B$1/99)-INT((ROW()-5)*B$1/99) -> 1 | C6: =INT((ROW()-4)*C$1/99)-INT((ROW()-5)*C$1/99) -> 1 | D6: =INT((ROW()-4)*D$1/99)-INT((ROW()-5)*D$1/99) -> 0 | E6: =INT((ROW()-4)*E$1/99)-INT((ROW()-5)*E$1/99) -> 0 | F6: =$B6*$C6 -> 1 | G6: =$B6*$D6 -> 0 | H6: =$B6*$E6 -> 0 | I6: =$C6*$D6 -> 0 | J6: =$C6*$E6 -> 0 | K6: =$D6*$E6 -> 0 | M6: A | N6: Economia pessoal (pupança, investimentos, etc) | O6: =SUM(B6:B104) -> 82
A7: =ROW()-4 -> 3 | B7: =INT((ROW()-4)*B$1/99)-INT((ROW()-5)*B$1/99) -> 1 | C7: =INT((ROW()-4)*C$1/99)-INT((ROW()-5)*C$1/99) -> 0 | D7: =INT((ROW()-4)*D$1/99)-INT((ROW()-5)*D$1/99) -> 1 | E7: =INT((ROW()-4)*E$1/99)-INT((ROW()-5)*E$1/99) -> 1 | F7: =$B7*$C7 -> 0 | G7: =$B7*$D7 -> 1 | H7: =$B7*$E7 -> 1 | I7: =$C7*$D7 -> 0 | J7: =$C7*$E7 -> 0 | K7: =$D7*$E7 -> 1 | M7: B | N7: Pensão do governo | O7: =SUM(C6:C104) -> 64
A8: =ROW()-4 -> 4 | B8: =INT((ROW()-4)*B$1/99)-INT((ROW()-5)*B$1/99) -> 1 | C8: =INT((ROW()-4)*C$1/99)-INT((ROW()-5)*C$1/99) -> 1 | D8: =INT((ROW()-4)*D$1/99)-INT((ROW()-5)*D$1/99) -> 0 | E8: =INT((ROW()-4)*E$1/99)-INT((ROW()-5)*E$1/99) -> 0 | F8: =$B8*$C8 -> 1 | G8: =$B8*$D8 -> 0 | H8: =$B8*$E8 -> 0 | I8: =$C8*$D8 -> 0 | J8: =$C8*$E8 -> 0 | K8: =$D8*$E8 -> 0 | M8: C | N8: Aposentadoria privada | O8: =SUM(D6:D104) -> 48
A9: =ROW()-4 -> 5 | B9: =INT((ROW()-4)*B$1/99)-INT((ROW()-5)*B$1/99) -> 1 | C9: =INT((ROW()-4)*C$1/99)-INT((ROW()-5)*C$1/99) -> 1 | D9: =INT((ROW()-4)*D$1/99)-INT((ROW()-5)*D$1/99) -> 1 | E9: =INT((ROW()-4)*E$1/99)-INT((ROW()-5)*E$1/99) -> 1 | F9: =$B9*$C9 -> 1 | G9: =$B9*$D9 -> 1 | H9: =$B9*$E9 -> 1 | I9: =$C9*$D9 -> 1 | J9: =$C9*$E9 -> 1 | K9: =$D9*$E9 -> 1 | M9: D | N9: Venda/aluguel de propriedades ou imóveis | O9: =SUM(E6:E104) -> 42
A10: =ROW()-4 -> 6 | B10: =INT((ROW()-4)*B$1/99)-INT((ROW()-5)*B$1/99) -> 0 | C10: =INT((ROW()-4)*C$1/99)-INT((ROW()-5)*C$1/99) -> 0 | D10: =INT((ROW()-4)*D$1/99)-INT((ROW()-5)*D$1/99) -> 0 | E10: =INT((ROW()-4)*E$1/99)-INT((ROW()-5)*E$1/99) -> 0 | F10: =$B10*$C10 -> 0 | G10: =$B10*$D10 -> 0 | H10: =$B10*$E10 -> 0 | I10: =$C10*$D10 -> 0 | J10: =$C10*$E10 -> 0 | K10: =$D10*$E10 -> 0 | M10: A∩B | N10: =$N$6&" + "&$N$7 -> Economia pessoal (pupança, investimentos, etc) + Pensão do governo | O10: =SUM(F6:F104) -> 52
A11: =ROW()-4 -> 7 | B11: =INT((ROW()-4)*B$1/99)-INT((ROW()-5)*B$1/99) -> 1 | C11: =INT((ROW()-4)*C$1/99)-INT((ROW()-5)*C$1/99) -> 1 | D11: =INT((ROW()-4)*D$1/99)-INT((ROW()-5)*D$1/99) -> 1 | E11: =INT((ROW()-4)*E$1/99)-INT((ROW()-5)*E$1/99) -> 0 | F11: =$B11*$C11 -> 1 | G11: =$B11*$D11 -> 1 | H11: =$B11*$E11 -> 0 | I11: =$C11*$D11 -> 1 | J11: =$C11*$E11 -> 0 | K11: =$D11*$E11 -> 0 | M11: A∩C | N11: =$N$6&" + "&$N$8 -> Economia pessoal (pupança, investimentos, etc) + Aposentadoria privada | O11: =SUM(G6:G104) -> 48
A12: =ROW()-4 -> 8 | B12: =INT((ROW()-4)*B$1/99)-INT((ROW()-5)*B$1/99) -> 1 | C12: =INT((ROW()-4)*C$1/99)-INT((ROW()-5)*C$1/99) -> 1 | D12: =INT((ROW()-4)*D$1/99)-INT((ROW()-5)*D$1/99) -> 0 | E12: =INT((ROW()-4)*E$1/99)-INT((ROW()-5)*E$1/99) -> 1 | F12: =$B12*$C12 -> 1 | G12: =$B12*$D12 -> 0 | H12: =$B12*$E12 -> 1 | I12: =$C12*$D12 -> 0 | J12: =$C12*$E12 -> 1 | K12: =$D12*$E12 -> 0 | M12: A∩D | N12: =$N$6&" + "&$N$9 -> Economia pessoal (pupança, investimentos, etc) + Venda/aluguel de propriedades ou imóveis | O12: =SUM(H6:H104) -> 36
A13: =ROW()-4 -> 9 | B13: =INT((ROW()-4)*B$1/99)-INT((ROW()-5)*B$1/99) -> 1 | C13: =INT((ROW()-4)*C$1/99)-INT((ROW()-5)*C$1/99) -> 0 | D13: =INT((ROW()-4)*D$1/99)-INT((ROW()-5)*D$1/99) -> 1 | E13: =INT((ROW()-4)*E$1/99)-INT((ROW()-5)*E$1/99) -> 0 | F13: =$B13*$C13 -> 0 | G13: =$B13*$D13 -> 1 | H13: =$B13*$E13 -> 0 | I13: =$C13*$D13 -> 0 | J13: =$C13*$E13 -> 0 | K13: =$D13*$E13 -> 0 | M13: B∩C | N13: =$N$7&" + "&$N$8 -> Pensão do governo + Aposentadoria privada | O13: =SUM(I6:I104) -> 31
A14: =ROW()-4 -> 10 | B14: =INT((ROW()-4)*B$1/99)-INT((ROW()-5)*B$1/99) -> 1 | C14: =INT((ROW()-4)*C$1/99)-INT((ROW()-5)*C$1/99) -> 1 | D14: =INT((ROW()-4)*D$1/99)-INT((ROW()-5)*D$1/99) -> 0 | E14: =INT((ROW()-4)*E$1/99)-INT((ROW()-5)*E$1/99) -> 1 | F14: =$B14*$C14 -> 1 | G14: =$B14*$D14 -> 0 | H14: =$B14*$E14 -> 1 | I14: =$C14*$D14 -> 0 | J14: =$C14*$E14 -> 1 | K14: =$D14*$E14 -> 0 | M14: B∩D | N14: =$N$7&" + "&$N$9 -> Pensão do governo + Venda/aluguel de propriedades ou imóveis | O14: =SUM(J6:J104) -> 27
A15: =ROW()-4 -> 11 | B15: =INT((ROW()-4)*B$1/99)-INT((ROW()-5)*B$1/99) -> 1 | C15: =INT((ROW()-4)*C$1/99)-INT((ROW()-5)*C$1/99) -> 1 | D15: =INT((ROW()-4)*D$1/99)-INT((ROW()-5)*D$1/99) -> 1 | E15: =INT((ROW()-4)*E$1/99)-INT((ROW()-5)*E$1/99) -> 0 | F15: =$B15*$C15 -> 1 | G15: =$B15*$D15 -> 1 | H15: =$B15*$E15 -> 0 | I15: =$C15*$D15 -> 1 | J15: =$C15*$E15 -> 0 | K15: =$D15*$E15 -> 0 | M15: C∩D | N15: =$N$8&" + "&$N$9 -> Aposentadoria privada + Venda/aluguel de propriedades ou imóveis | O15: =SUM(K6:K104) -> 24
A16: =ROW()-4 -> 12 | B16: =INT((ROW()-4)*B$1/99)-INT((ROW()-5)*B$1/99) -> 0 | C16: =INT((ROW()-4)*C$1/99)-INT((ROW()-5)*C$1/99) -> 0 | D16: =INT((ROW()-4)*D$1/99)-INT((ROW()-5)*D$1/99) -> 0 | E16: =INT((ROW()-4)*E$1/99)-INT((ROW()-5)*E$1/99) -> 1 | F16: =$B16*$C16 -> 0 | G16: =$B16*$D16 -> 0 | H16: =$B16*$E16 -> 0 | I16: =$C16*$D16 -> 0 | J16: =$C16*$E16 -> 0 | K16: =$D16*$E16 -> 0
A17: =ROW()-4 -> 13 | B17: =INT((ROW()-4)*B$1/99)-INT((ROW()-5)*B$1/99) -> 1 | C17: =INT((ROW()-4)*C$1/99)-INT((ROW()-5)*C$1/99) -> 1 | D17: =INT((ROW()-4)*D$1/99)-INT((ROW()-5)*D$1/99) -> 1 | E17: =INT((ROW()-4)*E$1/99)-INT((ROW()-5)*E$1/99) -> 0 | F17: =$B17*$C17 -> 1 | G17: =$B17*$D17 -> 1 | H17: =$B17*$E17 -> 0 | I17: =$C17*$D17 -> 1 | J17: =$C17*$E17 -> 0 | K17: =$D17*$E17 -> 0
A18: =ROW()-4 -> 14 | B18: =INT((ROW()-4)*B$1/99)-INT((ROW()-5)*B$1/99) -> 1 | C18: =INT((ROW()-4)*C$1/99)-INT((ROW()-5)*C$1/99) -> 1 | D18: =INT((ROW()-4)*D$1/99)-INT((ROW()-5)*D$1/99) -> 0 | E18: =INT((ROW()-4)*E$1/99)-INT((ROW()-5)*E$1/99) -> 0 | F18: =$B18*$C18 -> 1 | G18: =$B18*$D18 -> 0 | H18: =$B18*$E18 -> 0 | I18: =$C18*$D18 -> 0 | J18: =$C18*$E18 -> 0 | K18: =$D18*$E18 -> 0
A19: =ROW()-4 -> 15 | B19: =INT((ROW()-4)*B$1/99)-INT((ROW()-5)*B$1/99) -> 1 | C19: =INT((ROW()-4)*C$1/99)-INT((ROW()-5)*C$1/99) -> 0 | D19: =INT((ROW()-4)*D$1/99)-INT((ROW()-5)*D$1/99) -> 1 | E19: =INT((ROW()-4)*E$1/99)-INT((ROW()-5)*E$1/99) -> 1 | F19: =$B19*$C19 -> 0 | G19: =$B19*$D19 -> 1 | H19: =$B19*$E19 -> 1 | I19: =$C19*$D19 -> 0 | J19: =$C19*$E19 -> 0 | K19: =$D19*$E19 -> 1
A20: =ROW()-4 -> 16 | B20: =INT((ROW()-4)*B$1/99)-INT((ROW()-5)*B$1/99) -> 1 | C20: =INT((ROW()-4)*C$1/99)-INT((ROW()-5)*C$1/99) -> 1 | D20: =INT((ROW()-4)*D$1/99)-INT((ROW()-5)*D$1/99) -> 0 | E20: =INT((ROW()-4)*E$1/99)-INT((ROW()-5)*E$1/99) -> 0 | F20: =$B20*$C20 -> 1 | G20: =$B20*$D20 -> 0 | H20: =$B20*$E20 -> 0 | I20: =$C20*$D20 -> 0 | J20: =$C20*$E20 -> 0 | K20: =$D20*$E20 -> 0
A21: =ROW()-4 -> 17 | B21: =INT((ROW()-4)*B$1/99)-INT((ROW()-5)*B$1/99) -> 1 | C21: =INT((ROW()-4)*C$1/99)-INT((ROW()-5)*C$1/99) -> 0 | D21: =INT((ROW()-4)*D$1/99)-INT((ROW()-5)*D$1/99) -> 1 | E21: =INT((ROW()-4)*E$1/99)-INT((ROW()-5)*E$1/99) -> 1 | F21: =$B21*$C21 -> 0 | G21: =$B21*$D21 -> 1 | H21: =$B21*$E21 -> 1 | I21: =$C21*$D21 -> 0 | J21: =$C21*$E21 -> 0 | K21: =$D21*$E21 -> 1
A22: =ROW()-4 -> 18 | B22: =INT((ROW()-4)*B$1/99)-INT((ROW()-5)*B$1/99) -> 0 | C22: =INT((ROW()-4)*C$1/99)-INT((ROW()-5)*C$1/99) -> 1 | D22: =INT((ROW()-4)*D$1/99)-INT((ROW()-5)*D$1/99) -> 0 | E22: =INT((ROW()-4)*E$1/99)-INT((ROW()-5)*E$1/99) -> 0 | F22: =$B22*$C22 -> 0 | G22: =$B22*$D22 -> 0 | H22: =$B22*$E22 -> 0 | I22: =$C22*$D22 -> 0 | J22: =$C22*$E22 -> 0 | K22: =$D22*$E22 -> 0
A23: =ROW()-4 -> 19 | B23: =INT((ROW()-4)*B$1/99)-INT((ROW()-5)*B$1/99) -> 1 | C23: =INT((ROW()-4)*C$1/99)-INT((ROW()-5)*C$1/99) -> 1 | D23: =INT((ROW()-4)*D$1/99)-INT((ROW()-5)*D$1/99) -> 1 | E23: =INT((ROW()-4)*E$1/99)-INT((ROW()-5)*E$1/99) -> 1 | F23: =$B23*$C23 -> 1 | G23: =$B23*$D23 -> 1 | H23: =$B23*$E23 -> 1 | I23: =$C23*$D23 -> 1 | J23: =$C23*$E23 -> 1 | K23: =$D23*$E23 -> 1
A24: =ROW()-4 -> 20 | B24: =INT((ROW()-4)*B$1/99)-INT((ROW()-5)*B$1/99) -> 1 | C24: =INT((ROW()-4)*C$1/99)-INT((ROW()-5)*C$1/99) -> 0 | D24: =INT((ROW()-4)*D$1/99)-INT((ROW()-5)*D$1/99) -> 0 | E24: =INT((ROW()-4)*E$1/99)-INT((ROW()-5)*E$1/99) -> 0 | F24: =$B24*$C24 -> 0 | G24: =$B24*$D24 -> 0 | H24: =$B24*$E24 -> 0 | I24: =$C24*$D24 -> 0 | J24: =$C24*$E24 -> 0 | K24: =$D24*$E24 -> 0
A25: =ROW()-4 -> 21 | B25: =INT((ROW()-4)*B$1/99)-INT((ROW()-5)*B$1/99) -> 1 | C25: =INT((ROW()-4)*C$1/99)-INT((ROW()-5)*C$1/99) -> 1 | D25: =INT((ROW()-4)*D$1/99)-INT((ROW()-5)*D$1/99) -> 1 | E25: =INT((ROW()-4)*E$1/99)-INT((ROW()-5)*E$1/99) -> 0 | F25: =$B25*$C25 -> 1 | G25: =$B25*$D25 -> 1 | H25: =$B25*$E25 -> 0 | I25: =$C25*$D25 -> 1 | J25: =$C25*$E25 -> 0 | K25: =$D25*$E25 -> 0
A26: =ROW()-4 -> 22 | B26: =INT((ROW()-4)*B$1/99)-INT((ROW()-5)*B$1/99) -> 1 | C26: =INT((ROW()-4)*C$1/99)-INT((ROW()-5)*C$1/99) -> 1 | D26: =INT((ROW()-4)*D$1/99)-INT((ROW()-5)*D$1/99) -> 0 | E26: =INT((ROW()-4)*E$1/99)-INT((ROW()-5)*E$1/99) -> 1 | F26: =$B26*$C26 -> 1 | G26: =$B26*$D26 -> 0 | H26: =$B26*$E26 -> 1 | I26: =$C26*$D26 -> 0 | J26: =$C26*$E26 -> 1 | K26: =$D26*$E26 -> 0
A27: =ROW()-4 -> 23 | B27: =INT((ROW()-4)*B$1/99)-INT((ROW()-5)*B$1/99) -> 1 | C27: =INT((ROW()-4)*C$1/99)-INT((ROW()-5)*C$1/99) -> 0 | D27: =INT((ROW()-4)*D$1/99)-INT((ROW()-5)*D$1/99) -> 1 | E27: =INT((ROW()-4)*E$1/99)-INT((ROW()-5)*E$1/99) -> 0 | F27: =$B27*$C27 -> 0 | G27: =$B27*$D27 -> 1 | H27: =$B27*$E27 -> 0 | I27: =$C27*$D27 -> 0 | J27: =$C27*$E27 -> 0 | K27: =$D27*$E27 -> 0
... A104: =ROW()-4 -> 100 | B104: =INT((ROW()-4)*B$1/99)-INT((ROW()-5)*B$1/99) -> 0 | C104: =INT((ROW()-4)*C$1/99)-INT((ROW()-5)*C$1/99) -> 0 | D104: =INT((ROW()-4)*D$1/99)-INT((ROW()-5)*D$1/99) -> 0 | E104: =INT((ROW()-4)*E$1/99)-INT((ROW()-5)*E$1/99) -> 0 | F104: =$B104*$C104 -> 0 | G104: =$B104*$D104 -> 0 | H104: =$B104*$E104 -> 0 | I104: =$C104*$D104 -> 0 | J104: =$C104*$E104 -> 0 | K104: =$D104*$E104 -> 0

Sheet UpSet
A1: Combo | B1: A | C1: B | D1: C | E1: D | F1: Qtd | G1: Chave
A2: =_xlfn.TEXTJOIN("",TRUE,IF($B2=1,"A",""),IF($C2=1,"B",""),IF($D2=1,"C",""),IF($E2=1,"D","")) -> D | B2: 0 | C2: 0 | D2: 0 | E2: 1 | F2: =COUNTIFS(Planilha1!$B$6:$B$104,$B2,Planilha1!$C$6:$C$104,$C2,Planilha1!$D$6:$D$104,$D2,Planilha1!$E$6:$E$104,$E2) -> 2 | G2: =$F2*1000-ROW() -> 1998
A3: =_xlfn.TEXTJOIN("",TRUE,IF($B3=1,"A",""),IF($C3=1,"B",""),IF($D3=1,"C",""),IF($E3=1,"D","")) -> C | B3: 0 | C3: 0 | D3: 1 | E3: 0 | F3: =COUNTIFS(Planilha1!$B$6:$B$104,$B3,Planilha1!$C$6:$C$104,$C3,Planilha1!$D$6:$D$104,$D3,Planilha1!$E$6:$E$104,$E3) -> 0 | G3: =$F3*1000-ROW() -> -3
A4: =_xlfn.TEXTJOIN("",TRUE,IF($B4=1,"A",""),IF($C4=1,"B",""),IF($D4=1,"C",""),IF($E4=1,"D","")) -> CD | B4: 0 | C4: 0 | D4: 1 | E4: 1 | F4: =COUNTIFS(Planilha1!$B$6:$B$104,$B4,Planilha1!$C$6:$C$104,$C4,Planilha1!$D$6:$D$104,$D4,Planilha1!$E$6:$E$104,$E4) -> 0 | G4: =$F4*1000-ROW() -> -4
A5: =_xlfn.TEXTJOIN("",TRUE,IF($B5=1,"A",""),IF($C5=1,"B",""),IF($D5=1,"C",""),IF($E5=1,"D","")) -> B | B5: 0 | C5: 1 | D5: 0 | E5: 0 | F5: =COUNTIFS(Planilha1!$B$6:$B$104,$B5,Planilha1!$C$6:$C$104,$C5,Planilha1!$D$6:$D$104,$D5,Planilha1!$E$6:$E$104,$E5) -> 8 | G5: =$F5*1000-ROW() -> 7995
A6: =_xlfn.TEXTJOIN("",TRUE,IF($B6=1,"A",""),IF($C6=1,"B",""),IF($D6=1,"C",""),IF($E6=1,"D","")) -> BD | B6: 0 | C6: 1 | D6: 0 | E6: 1 | F6: =COUNTIFS(Planilha1!$B$6:$B$104,$B6,Planilha1!$C$6:$C$104,$C6,Planilha1!$D$6:$D$104,$D6,Planilha1!$E$6:$E$104,$E6) -> 4 | G6: =$F6*1000-ROW() -> 3994
A7: =_xlfn.TEXTJOIN("",TRUE,IF($B7=1,"A",""),IF($C7=1,"B",""),IF($D7=1,"C",""),IF($E7=1,"D","")) -> BC | B7: 0 | C7: 1 | D7: 1 | E7: 0 | F7: =COUNTIFS(Planilha1!$B$6:$B$104,$B7,Planilha1!$C$6:$C$104,$C7,Planilha1!$D$6:$D$104,$D7,Planilha1!$E$6:$E$104,$E7) -> 0 | G7: =$F7*1000-ROW() -> -7
A8: =_xlfn.TEXTJOIN("",TRUE,IF($B8=1,"A",""),IF($C8=1,"B",""),IF($D8=1,"C",""),IF($E8=1,"D","")) -> BCD | B8: 0 | C8: 1 | D8: 1 | E8: 1 | F8: =COUNTIFS(Planilha1!$B$6:$B$104,$B8,Planilha1!$C$6:$C$104,$C8,Planilha1!$D$6:$D$104,$D8,Planilha1!$E$6:$E$104,$E8) -> 0 | G8: =$F8*1000-ROW() -> -8
A9: =_xlfn.TEXTJOIN("",TRUE,IF($B9=1,"A",""),IF($C9=1,"B",""),IF($D9=1,"C",""),IF($E9=1,"D","")) -> A | B9: 1 | C9: 0 | D9: 0 | E9: 0 | F9: =COUNTIFS(Planilha1!$B$6:$B$104,$B9,Planilha1!$C$6:$C$104,$C9,Planilha1!$D$6:$D$104,$D9,Planilha1!$E$6:$E$104,$E9) -> 9 | G9: =$F9*1000-ROW() -> 8991
A10: =_xlfn.TEXTJOIN("",TRUE,IF($B10=1,"A",""),IF($C10=1,"B",""),IF($D10=1,"C",""),IF($E10=1,"D","")) -> AD | B10: 1 | C10: 0 | D10: 0 | E10: 1 | F10: =COUNTIFS(Planilha1!$B$6:$B$104,$B10,Planilha1!$C$6:$C$104,$C10,Planilha1!$D$6:$D$104,$D10,Planilha1!$E$6:$E$104,$E10) -> 4 | G10: =$F10*1000-ROW() -> 3990
A11: =_xlfn.TEXTJOIN("",TRUE,IF($B11=1,"A",""),IF($C11=1,"B",""),IF($D11=1,"C",""),IF($E11=1,"D","")) -> AC | B11: 1 | C11: 0 | D11: 1 | E11: 0 | F11: =COUNTIFS(Planilha1!$B$6:$B$104,$B11,Planilha1!$C$6:$C$104,$C11,Planilha1!$D$6:$D$104,$D11,Planilha1!$E$6:$E$104,$E11) -> 8 | G11: =$F11*1000-ROW() -> 7989
A12: =_xlfn.TEXTJOIN("",TRUE,IF($B12=1,"A",""),IF($C12=1,"B",""),IF($D12=1,"C",""),IF($E12=1,"D","")) -> ACD | B12: 1 | C12: 0 | D12: 1 | E12: 1 | F12: =COUNTIFS(Planilha1!$B$6:$B$104,$B12,Planilha1!$C$6:$C$104,$C12,Planilha1!$D$6:$D$104,$D12,Planilha1!$E$6:$E$104,$E12) -> 9 | G12: =$F12*1000-ROW() -> 8988
A13: =_xlfn.TEXTJOIN("",TRUE,IF($B13=1,"A",""),IF($C13=1,"B",""),IF($D13=1,"C",""),IF($E13=1,"D","")) -> AB | B13: 1 | C13: 1 | D13: 0 | E13: 0 | F13: =COUNTIFS(Planilha1!$B$6:$B$104,$B13,Planilha1!$C$6:$C$104,$C13,Planilha1!$D$6:$D$104,$D13,Planilha1!$E$6:$E$104,$E13) -> 13 | G13: =$F13*1000-ROW() -> 12987
... A16: =_xlfn.TEXTJOIN("",TRUE,IF($B16=1,"A",""),IF($C16=1,"B",""),IF($D16=1,"C",""),IF($E16=1,"D","")) -> ABCD | B16: 1 | C16: 1 | D16: 1 | E16: 1 | F16: =COUNTIFS(Planilha1!$B$6:$B$104,$B16,Planilha1!$C$6:$C$104,$C16,Planilha1!$D$6:$D$104,$D16,Planilha1!$E$6:$E$104,$E16) -> 15 | G16: =$F16*1000-ROW() -> 14984
Q19: Tabela auxiliar (ordenação)
Q20: Rank | R20: 1 | S20: 2 | T20: 3 | U20: 4 | V20: 5 | W20: 6 | X20: 7 | Y20: 8 | Z20: 9 | AA20: 10 | AB20: 11
Q21: Combinação | R21: =INDEX($A$2:$A$16,MATCH(LARGE($G$2:$G$16,R$20),$G$2:$G$16,0)) -> ABC | S21: =INDEX($A$2:$A$16,MATCH(LARGE($G$2:$G$16,S$20),$G$2:$G$16,0)) -> ABCD | T21: =INDEX($A$2:$A$16,MATCH(LARGE($G$2:$G$16,T$20),$G$2:$G$16,0)) -> AB | U21: =INDEX($A$2:$A$16,MATCH(LARGE($G$2:$G$16,U$20),$G$2:$G$16,0)) -> A | V21: =INDEX($A$2:$A$16,MATCH(LARGE($G$2:$G$16,V$20),$G$2:$G$16,0)) -> ACD | W21: =INDEX($A$2:$A$16,MATCH(LARGE($G$2:$G$16,W$20),$G$2:$G$16,0)) -> B | X21: =INDEX($A$2:$A$16,MATCH(LARGE($G$2:$G$16,X$20),$G$2:$G$16,0)) -> AC | Y21: =INDEX($A$2:$A$16,MATCH(LARGE($G$2:$G$16,Y$20),$G$2:$G$16,0)) -> ABD | ... AB21: =INDEX($A$2:$A$16,MATCH(LARGE($G$2:$G$16,AB$20),$G$2:$G$16,0)) -> D
Q22: Qtd | R22: =INDEX($F$2:$F$16,MATCH(LARGE($G$2:$G$16,R$20),$G$2:$G$16,0)) -> 16 | S22: =INDEX($F$2:$F$16,MATCH(LARGE($G$2:$G$16,S$20),$G$2:$G$16,0)) -> 15 | T22: =INDEX($F$2:$F$16,MATCH(LARGE($G$2:$G$16,T$20),$G$2:$G$16,0)) -> 13 | U22: =INDEX($F$2:$F$16,MATCH(LARGE($G$2:$G$16,U$20),$G$2:$G$16,0)) -> 9 | V22: =INDEX($F$2:$F$16,MATCH(LARGE($G$2:$G$16,V$20),$G$2:$G$16,0)) -> 9 | W22: =INDEX($F$2:$F$16,MATCH(LARGE($G$2:$G$16,W$20),$G$2:$G$16,0)) -> 8 | X22: =INDEX($F$2:$F$16,MATCH(LARGE($G$2:$G$16,X$20),$G$2:$G$16,0)) -> 8 | Y22: =INDEX($F$2:$F$16,MATCH(LARGE($G$2:$G$16,Y$20),$G$2:$G$16,0)) -> 8 | ... AB22: =INDEX($F$2:$F$16,MATCH(LARGE($G$2:$G$16,AB$20),$G$2:$G$16,0)) -> 2
B23: UpSet — combinações de fontes de renda na aposentadoria
B24: Tamanho da interseção exclusiva (nº de respondentes)
B34: Total do conjunto | C34: Conjunto
B35: =SUM(Planilha1!$B$6:$B$104) -> 82 | C35: A | D35: =IF(ISNUMBER(SEARCH($C35,R$21)),"●","○") -> ● | E35: =IF(ISNUMBER(SEARCH($C35,S$21)),"●","○") -> ● | F35: =IF(ISNUMBER(SEARCH($C35,T$21)),"●","○") -> ● | G35: =IF(ISNUMBER(SEARCH($C35,U$21)),"●","○") -> ● | H35: =IF(ISNUMBER(SEARCH($C35,V$21)),"●","○") -> ● | I35: =IF(ISNUMBER(SEARCH($C35,W$21)),"●","○") -> ○ | J35: =IF(ISNUMBER(SEARCH($C35,X$21)),"●","○") -> ● | K35: =IF(ISNUMBER(SEARCH($C35,Y$21)),"●","○") -> ● | ... N35: =IF(ISNUMBER(SEARCH($C35,AB$21)),"●","○") -> ○
B36: =SUM(Planilha1!$C$6:$C$104) -> 64 | C36: B | D36: =IF(ISNUMBER(SEARCH($C36,R$21)),"●","○") -> ● | E36: =IF(ISNUMBER(SEARCH($C36,S$21)),"●","○") -> ● | F36: =IF(ISNUMBER(SEARCH($C36,T$21)),"●","○") -> ● | G36: =IF(ISNUMBER(SEARCH($C36,U$21)),"●","○") -> ○ | H36: =IF(ISNUMBER(SEARCH($C36,V$21)),"●","○") -> ○ | I36: =IF(ISNUMBER(SEARCH($C36,W$21)),"●","○") -> ● | J36: =IF(ISNUMBER(SEARCH($C36,X$21)),"●","○") -> ○ | K36: =IF(ISNUMBER(SEARCH($C36,Y$21)),"●","○") -> ● | ... N36: =IF(ISNUMBER(SEARCH($C36,AB$21)),"●","○") -> ○
B37: =SUM(Planilha1!$D$6:$D$104) -> 48 | C37: C | D37: =IF(ISNUMBER(SEARCH($C37,R$21)),"●","○") -> ● | E37: =IF(ISNUMBER(SEARCH($C37,S$21)),"●","○") -> ● | F37: =IF(ISNUMBER(SEARCH($C37,T$21)),"●","○") -> ○ | G37: =IF(ISNUMBER(SEARCH($C37,U$21)),"●","○") -> ○ | H37: =IF(ISNUMBER(SEARCH($C37,V$21)),"●","○") -> ● | I37: =IF(ISNUMBER(SEARCH($C37,W$21)),"●","○") -> ○ | J37: =IF(ISNUMBER(SEARCH($C37,X$21)),"●","○") -> ● | K37: =IF(ISNUMBER(SEARCH($C37,Y$21)),"●","○") -> ○ | ... N37: =IF(ISNUMBER(SEARCH($C37,AB$21)),"●","○") -> ○
B38: =SUM(Planilha1!$E$6:$E$104) -> 42 | C38: D | D38: =IF(ISNUMBER(SEARCH($C38,R$21)),"●","○") -> ○ | E38: =IF(ISNUMBER(SEARCH($C38,S$21)),"●","○") -> ● | F38: =IF(ISNUMBER(SEARCH($C38,T$21)),"●","○") -> ○ | G38: =IF(ISNUMBER(SEARCH($C38,U$21)),"●","○") -> ○ | H38: =IF(ISNUMBER(SEARCH($C38,V$21)),"●","○") -> ● | I38: =IF(ISNUMBER(SEARCH($C38,W$21)),"●","○") -> ○ | J38: =IF(ISNUMBER(SEARCH($C38,X$21)),"●","○") -> ○ | K38: =IF(ISNUMBER(SEARCH($C38,Y$21)),"●","○") -> ● | ... N38: =IF(ISNUMBER(SEARCH($C38,AB$21)),"●","○") -> ●
B40: n = 99 respondentes. Cada pessoa conta em uma única combinação; 3 não marcaram nenhuma opção. Combinações vazias omitidas.
B42: Legenda
B43: A | C43: =Planilha1!$N$6 -> Economia pessoal (pupança, investimentos, etc)
B44: B | C44: =Planilha1!$N$7 -> Pensão do governo
B45: C | C45: =Planilha1!$N$8 -> Aposentadoria privada
B46: D | C46: =Planilha1!$N$9 -> Venda/aluguel de propriedades ou imóveis
