Workbook

Sheet Dashboard
A1: DASHBOARD DE PRODUÇÃO INTELECTUAL
A2: Fonte: aba Matriz (projetos × 12 canais) e aba Periódicos. Todos os indicadores são fórmulas.
A4: Projetos cadastrados | C4: Saídas concluídas (canais) | E4: Links registrados | G4: Cobertura geral | I4: Média saídas/projeto | K4: Projetos multicanal (≥3)
A5: =COUNTIF(Matriz!$C$2:$C$60,"<>") -> 47 | C5: =SUM(Matriz!$AE$2:$AE$60) -> 111 | E5: =SUM(Matriz!$AF$2:$AF$60) -> 59 | G5: =IFERROR($C$5/($A$5*12),0) -> 0.19680851 | I5: =IFERROR($C$5/$A$5,0) -> 2.3617021 | K5: =COUNTIF(Matriz!$AE$2:$AE$60,">=3") -> 8
A7: Projetos com ≥1 saída | C7: Projetos sem saída | E7: Temas ativos | G7: Canais ativos | I7: Periódicos mapeados | K7: Periódicos fit ≥4
A8: =COUNTIF(Matriz!$AE$2:$AE$60,">=1") -> 47 | C8: =COUNTIF(Matriz!$AE$2:$AE$60,0) -> 0 | E8: =COUNTIF($C$12:$C$23,">0") -> 12 | G8: =COUNTIF($H$12:$H$23,">0") -> 6 | I8: =COUNTIF(Periódicos!$A$2:$A$168,"<>") -> 167 | K8: =COUNTIF(Periódicos!$I$2:$I$168,">=4") -> 113
A10: PRODUÇÃO POR TEMA | G10: PRODUÇÃO POR CANAL
A11: Tema | B11: Saídas concluídas | C11: Projetos | D11: Links | E11: Cobertura | G11: Canal | H11: Saídas concluídas | I11: Links | J11: Cobertura
A12: Álgebra | B12: =SUMIF(Matriz!$B$2:$B$60,$A12,Matriz!$AE$2:$AE$60) -> 4 | C12: =COUNTIFS(Matriz!$B$2:$B$60,$A12,Matriz!$C$2:$C$60,"<>") -> 2 | D12: =SUMIF(Matriz!$B$2:$B$60,$A12,Matriz!$AF$2:$AF$60) -> 2 | E12: =IFERROR($B12/($C12*12),0) -> 0.16666667 | G12: arXiv/SSRN | H12: =SUM(INDEX(Matriz!$F$2:$Q$60,0,MATCH($G12,Matriz!$F$1:$Q$1,0))) -> 8 | I12: =COUNTIF(INDEX(Matriz!$R$2:$AC$60,0,MATCH($G12&" (link)",Matriz!$R$1:$AC$1,0)),"http*") -> 8 | J12: =IFERROR($H12/$A$5,0) -> 0.17021277
A13: algebra | B13: =SUMIF(Matriz!$B$2:$B$60,$A13,Matriz!$AE$2:$AE$60) -> 2 | C13: =COUNTIFS(Matriz!$B$2:$B$60,$A13,Matriz!$C$2:$C$60,"<>") -> 1 | D13: =SUMIF(Matriz!$B$2:$B$60,$A13,Matriz!$AF$2:$AF$60) -> 1 | E13: =IFERROR($B13/($C13*12),0) -> 0.16666667 | G13: Journal | H13: =SUM(INDEX(Matriz!$F$2:$Q$60,0,MATCH($G13,Matriz!$F$1:$Q$1,0))) -> 8 | I13: =COUNTIF(INDEX(Matriz!$R$2:$AC$60,0,MATCH($G13&" (link)",Matriz!$R$1:$AC$1,0)),"http*") -> 8 | J13: =IFERROR($H13/$A$5,0) -> 0.17021277
A14: Análise de dados | B14: =SUMIF(Matriz!$B$2:$B$60,$A14,Matriz!$AE$2:$AE$60) -> 6 | C14: =COUNTIFS(Matriz!$B$2:$B$60,$A14,Matriz!$C$2:$C$60,"<>") -> 3 | D14: =SUMIF(Matriz!$B$2:$B$60,$A14,Matriz!$AF$2:$AF$60) -> 3 | E14: =IFERROR($B14/($C14*12),0) -> 0.16666667 | G14: Research Gate | H14: =SUM(INDEX(Matriz!$F$2:$Q$60,0,MATCH($G14,Matriz!$F$1:$Q$1,0))) -> 8 | I14: =COUNTIF(INDEX(Matriz!$R$2:$AC$60,0,MATCH($G14&" (link)",Matriz!$R$1:$AC$1,0)),"http*") -> 0 | J14: =IFERROR($H14/$A$5,0) -> 0.17021277
A15: Análise matemática | B15: =SUMIF(Matriz!$B$2:$B$60,$A15,Matriz!$AE$2:$AE$60) -> 16 | C15: =COUNTIFS(Matriz!$B$2:$B$60,$A15,Matriz!$C$2:$C$60,"<>") -> 8 | D15: =SUMIF(Matriz!$B$2:$B$60,$A15,Matriz!$AF$2:$AF$60) -> 8 | E15: =IFERROR($B15/($C15*12),0) -> 0.16666667 | G15: YouTube | H15: =SUM(INDEX(Matriz!$F$2:$Q$60,0,MATCH($G15,Matriz!$F$1:$Q$1,0))) -> 40 | I15: =COUNTIF(INDEX(Matriz!$R$2:$AC$60,0,MATCH($G15&" (link)",Matriz!$R$1:$AC$1,0)),"http*") -> 40 | J15: =IFERROR($H15/$A$5,0) -> 0.85106383
A16: Ciência de Dados e IA | B16: =SUMIF(Matriz!$B$2:$B$60,$A16,Matriz!$AE$2:$AE$60) -> 2 | C16: =COUNTIFS(Matriz!$B$2:$B$60,$A16,Matriz!$C$2:$C$60,"<>") -> 1 | D16: =SUMIF(Matriz!$B$2:$B$60,$A16,Matriz!$AF$2:$AF$60) -> 1 | E16: =IFERROR($B16/($C16*12),0) -> 0.16666667 | G16: TikTok | H16: =SUM(INDEX(Matriz!$F$2:$Q$60,0,MATCH($G16,Matriz!$F$1:$Q$1,0))) -> 40 | I16: =COUNTIF(INDEX(Matriz!$R$2:$AC$60,0,MATCH($G16&" (link)",Matriz!$R$1:$AC$1,0)),"http*") -> 2 | J16: =IFERROR($H16/$A$5,0) -> 0.85106383
A17: Estatística e Probabilidade | B17: =SUMIF(Matriz!$B$2:$B$60,$A17,Matriz!$AE$2:$AE$60) -> 2 | C17: =COUNTIFS(Matriz!$B$2:$B$60,$A17,Matriz!$C$2:$C$60,"<>") -> 1 | D17: =SUMIF(Matriz!$B$2:$B$60,$A17,Matriz!$AF$2:$AF$60) -> 1 | E17: =IFERROR($B17/($C17*12),0) -> 0.16666667 | G17: LinkedIn | H17: =SUM(INDEX(Matriz!$F$2:$Q$60,0,MATCH($G17,Matriz!$F$1:$Q$1,0))) -> 0 | I17: =COUNTIF(INDEX(Matriz!$R$2:$AC$60,0,MATCH($G17&" (link)",Matriz!$R$1:$AC$1,0)),"http*") -> 0 | J17: =IFERROR($H17/$A$5,0) -> 0
A18: Física Clássica | B18: =SUMIF(Matriz!$B$2:$B$60,$A18,Matriz!$AE$2:$AE$60) -> 26 | C18: =COUNTIFS(Matriz!$B$2:$B$60,$A18,Matriz!$C$2:$C$60,"<>") -> 10 | D18: =SUMIF(Matriz!$B$2:$B$60,$A18,Matriz!$AF$2:$AF$60) -> 15 | E18: =IFERROR($B18/($C18*12),0) -> 0.21666667 | G18: Newsletter LinkedIn | H18: =SUM(INDEX(Matriz!$F$2:$Q$60,0,MATCH($G18,Matriz!$F$1:$Q$1,0))) -> 0 | I18: =COUNTIF(INDEX(Matriz!$R$2:$AC$60,0,MATCH($G18&" (link)",Matriz!$R$1:$AC$1,0)),"http*") -> 0 | J18: =IFERROR($H18/$A$5,0) -> 0
A19: Física Quântica | B19: =SUMIF(Matriz!$B$2:$B$60,$A19,Matriz!$AE$2:$AE$60) -> 2 | C19: =COUNTIFS(Matriz!$B$2:$B$60,$A19,Matriz!$C$2:$C$60,"<>") -> 1 | D19: =SUMIF(Matriz!$B$2:$B$60,$A19,Matriz!$AF$2:$AF$60) -> 1 | E19: =IFERROR($B19/($C19*12),0) -> 0.16666667 | G19: Substack | H19: =SUM(INDEX(Matriz!$F$2:$Q$60,0,MATCH($G19,Matriz!$F$1:$Q$1,0))) -> 0 | I19: =COUNTIF(INDEX(Matriz!$R$2:$AC$60,0,MATCH($G19&" (link)",Matriz!$R$1:$AC$1,0)),"http*") -> 0 | J19: =IFERROR($H19/$A$5,0) -> 0
A20: Geometria | B20: =SUMIF(Matriz!$B$2:$B$60,$A20,Matriz!$AE$2:$AE$60) -> 14 | C20: =COUNTIFS(Matriz!$B$2:$B$60,$A20,Matriz!$C$2:$C$60,"<>") -> 7 | D20: =SUMIF(Matriz!$B$2:$B$60,$A20,Matriz!$AF$2:$AF$60) -> 8 | E20: =IFERROR($B20/($C20*12),0) -> 0.16666667 | G20: GitHub | H20: =SUM(INDEX(Matriz!$F$2:$Q$60,0,MATCH($G20,Matriz!$F$1:$Q$1,0))) -> 7 | I20: =COUNTIF(INDEX(Matriz!$R$2:$AC$60,0,MATCH($G20&" (link)",Matriz!$R$1:$AC$1,0)),"http*") -> 1 | J20: =IFERROR($H20/$A$5,0) -> 0.14893617
A21: Programação | B21: =SUMIF(Matriz!$B$2:$B$60,$A21,Matriz!$AE$2:$AE$60) -> 6 | C21: =COUNTIFS(Matriz!$B$2:$B$60,$A21,Matriz!$C$2:$C$60,"<>") -> 3 | D21: =SUMIF(Matriz!$B$2:$B$60,$A21,Matriz!$AF$2:$AF$60) -> 3 | E21: =IFERROR($B21/($C21*12),0) -> 0.16666667 | G21: Oz.io | H21: =SUM(INDEX(Matriz!$F$2:$Q$60,0,MATCH($G21,Matriz!$F$1:$Q$1,0))) -> 0 | I21: =COUNTIF(INDEX(Matriz!$R$2:$AC$60,0,MATCH($G21&" (link)",Matriz!$R$1:$AC$1,0)),"http*") -> 0 | J21: =IFERROR($H21/$A$5,0) -> 0
A22: Teoria dos Números | B22: =SUMIF(Matriz!$B$2:$B$60,$A22,Matriz!$AE$2:$AE$60) -> 4 | C22: =COUNTIFS(Matriz!$B$2:$B$60,$A22,Matriz!$C$2:$C$60,"<>") -> 2 | D22: =SUMIF(Matriz!$B$2:$B$60,$A22,Matriz!$AF$2:$AF$60) -> 2 | E22: =IFERROR($B22/($C22*12),0) -> 0.16666667 | G22: Oz Site | H22: =SUM(INDEX(Matriz!$F$2:$Q$60,0,MATCH($G22,Matriz!$F$1:$Q$1,0))) -> 0 | I22: =COUNTIF(INDEX(Matriz!$R$2:$AC$60,0,MATCH($G22&" (link)",Matriz!$R$1:$AC$1,0)),"http*") -> 0 | J22: =IFERROR($H22/$A$5,0) -> 0
A23: Warp Drive | B23: =SUMIF(Matriz!$B$2:$B$60,$A23,Matriz!$AE$2:$AE$60) -> 27 | C23: =COUNTIFS(Matriz!$B$2:$B$60,$A23,Matriz!$C$2:$C$60,"<>") -> 8 | D23: =SUMIF(Matriz!$B$2:$B$60,$A23,Matriz!$AF$2:$AF$60) -> 14 | E23: =IFERROR($B23/($C23*12),0) -> 0.28125 | G23: Curso | H23: =SUM(INDEX(Matriz!$F$2:$Q$60,0,MATCH($G23,Matriz!$F$1:$Q$1,0))) -> 0 | I23: =COUNTIF(INDEX(Matriz!$R$2:$AC$60,0,MATCH($G23&" (link)",Matriz!$R$1:$AC$1,0)),"http*") -> 0 | J23: =IFERROR($H23/$A$5,0) -> 0
A24: Total | B24: =SUM($B$12:$B$23) -> 111 | C24: =SUM($C$12:$C$23) -> 47 | D24: =SUM($D$12:$D$23) -> 59 | E24: =IFERROR($B$24/($C$24*12),0) -> 0.19680851 | G24: Total | H24: =SUM($H$12:$H$23) -> 111 | I24: =SUM($I$12:$I$23) -> 59 | J24: =IFERROR($H$24/($A$5*12),0) -> 0.19680851
A26: TOP 10 PROJETOS POR SAÍDAS CONCLUÍDAS | I26: PERIÓDICOS (pipeline de submissão)
A27: Projeto | D27: Tema | E27: Saídas | F27: Links | G27: Cobertura | I27: Indicador | K27: Valor
A28: =IFERROR(INDEX(Matriz!$C$2:$C$60,MATCH(ROWS($A$28:$A28),Matriz!$AH$2:$AH$60,0)),"") -> O problema do SAT que todos erraram: paradoxo das moedas e roda de Aristóteles | D28: =IFERROR(INDEX(Matriz!$B$2:$B$60,MATCH(ROWS($A$28:$A28),Matriz!$AH$2:$AH$60,0)),"") -> Física Clássica | E28: =IFERROR(INDEX(Matriz!$AE$2:$AE$60,MATCH(ROWS($A$28:$A28),Matriz!$AH$2:$AH$60,0)),"") -> 6 | F28: =IFERROR(INDEX(Matriz!$AF$2:$AF$60,MATCH(ROWS($A$28:$A28),Matriz!$AH$2:$AH$60,0)),"") -> 4 | G28: =IFERROR($E28/12,0) -> 0.5 | I28: Periódicos mapeados | K28: =COUNTIF(Periódicos!$A$2:$A$168,"<>") -> 167
A29: =IFERROR(INDEX(Matriz!$C$2:$C$60,MATCH(ROWS($A$28:$A29),Matriz!$AH$2:$AH$60,0)),"") -> Experimento de medição da densidade da água | D29: =IFERROR(INDEX(Matriz!$B$2:$B$60,MATCH(ROWS($A$28:$A29),Matriz!$AH$2:$AH$60,0)),"") -> Física Clássica | E29: =IFERROR(INDEX(Matriz!$AE$2:$AE$60,MATCH(ROWS($A$28:$A29),Matriz!$AH$2:$AH$60,0)),"") -> 4 | F29: =IFERROR(INDEX(Matriz!$AF$2:$AF$60,MATCH(ROWS($A$28:$A29),Matriz!$AH$2:$AH$60,0)),"") -> 3 | G29: =IFERROR($E29/12,0) -> 0.33333333 | I29: Fit 5 (prioridade) | K29: =COUNTIF(Periódicos!$I$2:$I$168,5) -> 27
A30: =IFERROR(INDEX(Matriz!$C$2:$C$60,MATCH(ROWS($A$28:$A30),Matriz!$AH$2:$AH$60,0)),"") -> Fluid dynamics in the warp drive spacetime geometry | D30: =IFERROR(INDEX(Matriz!$B$2:$B$60,MATCH(ROWS($A$28:$A30),Matriz!$AH$2:$AH$60,0)),"") -> Warp Drive | E30: =IFERROR(INDEX(Matriz!$AE$2:$AE$60,MATCH(ROWS($A$28:$A30),Matriz!$AH$2:$AH$60,0)),"") -> 4 | F30: =IFERROR(INDEX(Matriz!$AF$2:$AF$60,MATCH(ROWS($A$28:$A30),Matriz!$AH$2:$AH$60,0)),"") -> 2 | G30: =IFERROR($E30/12,0) -> 0.33333333 | I30: Fit ≥4 | K30: =COUNTIF(Periódicos!$I$2:$I$168,">=4") -> 113
A31: =IFERROR(INDEX(Matriz!$C$2:$C$60,MATCH(ROWS($A$28:$A31),Matriz!$AH$2:$AH$60,0)),"") -> Charged dust solutions for the warp drive spacetime | D31: =IFERROR(INDEX(Matriz!$B$2:$B$60,MATCH(ROWS($A$28:$A31),Matriz!$AH$2:$AH$60,0)),"") -> Warp Drive | E31: =IFERROR(INDEX(Matriz!$AE$2:$AE$60,MATCH(ROWS($A$28:$A31),Matriz!$AH$2:$AH$60,0)),"") -> 4 | F31: =IFERROR(INDEX(Matriz!$AF$2:$AF$60,MATCH(ROWS($A$28:$A31),Matriz!$AH$2:$AH$60,0)),"") -> 2 | G31: =IFERROR($E31/12,0) -> 0.33333333 | I31: Impact Factor médio | K31: =IFERROR(AVERAGE(Periódicos!$D$2:$D$168),0) -> 6.8288611
A32: =IFERROR(INDEX(Matriz!$C$2:$C$60,MATCH(ROWS($A$28:$A32),Matriz!$AH$2:$AH$60,0)),"") -> Perfect fluid warp drive solutions with the cosmological constant | D32: =IFERROR(INDEX(Matriz!$B$2:$B$60,MATCH(ROWS($A$28:$A32),Matriz!$AH$2:$AH$60,0)),"") -> Warp Drive | E32: =IFERROR(INDEX(Matriz!$AE$2:$AE$60,MATCH(ROWS($A$28:$A32),Matriz!$AH$2:$AH$60,0)),"") -> 4 | F32: =IFERROR(INDEX(Matriz!$AF$2:$AF$60,MATCH(ROWS($A$28:$A32),Matriz!$AH$2:$AH$60,0)),"") -> 2 | G32: =IFERROR($E32/12,0) -> 0.33333333 | I32: Área: matemática | K32: =COUNTIF(Periódicos!$E$2:$E$168,"matemática") -> 140
A33: =IFERROR(INDEX(Matriz!$C$2:$C$60,MATCH(ROWS($A$28:$A33),Matriz!$AH$2:$AH$60,0)),"") -> Warp drive dynamic solutions considering different fluid sources | D33: =IFERROR(INDEX(Matriz!$B$2:$B$60,MATCH(ROWS($A$28:$A33),Matriz!$AH$2:$AH$60,0)),"") -> Warp Drive | E33: =IFERROR(INDEX(Matriz!$AE$2:$AE$60,MATCH(ROWS($A$28:$A33),Matriz!$AH$2:$AH$60,0)),"") -> 4 | F33: =IFERROR(INDEX(Matriz!$AF$2:$AF$60,MATCH(ROWS($A$28:$A33),Matriz!$AH$2:$AH$60,0)),"") -> 2 | G33: =IFERROR($E33/12,0) -> 0.33333333 | I33: Área: física | K33: =COUNTIF(Periódicos!$E$2:$E$168,"física") -> 26
A34: =IFERROR(INDEX(Matriz!$C$2:$C$60,MATCH(ROWS($A$28:$A34),Matriz!$AH$2:$AH$60,0)),"") -> Matching the Alcubierre and Minkowski spacetimes. | D34: =IFERROR(INDEX(Matriz!$B$2:$B$60,MATCH(ROWS($A$28:$A34),Matriz!$AH$2:$AH$60,0)),"") -> Warp Drive | E34: =IFERROR(INDEX(Matriz!$AE$2:$AE$60,MATCH(ROWS($A$28:$A34),Matriz!$AH$2:$AH$60,0)),"") -> 4 | F34: =IFERROR(INDEX(Matriz!$AF$2:$AF$60,MATCH(ROWS($A$28:$A34),Matriz!$AH$2:$AH$60,0)),"") -> 2 | G34: =IFERROR($E34/12,0) -> 0.33333333 | I34: Área: data science | K34: =COUNTIF(Periódicos!$E$2:$E$168,"data science") -> 1
A35: =IFERROR(INDEX(Matriz!$C$2:$C$60,MATCH(ROWS($A$28:$A35),Matriz!$AH$2:$AH$60,0)),"") -> Dust content content solutions for the Alcubierre warp drive spacetime. | D35: =IFERROR(INDEX(Matriz!$B$2:$B$60,MATCH(ROWS($A$28:$A35),Matriz!$AH$2:$AH$60,0)),"") -> Warp Drive | E35: =IFERROR(INDEX(Matriz!$AE$2:$AE$60,MATCH(ROWS($A$28:$A35),Matriz!$AH$2:$AH$60,0)),"") -> 3 | F35: =IFERROR(INDEX(Matriz!$AF$2:$AF$60,MATCH(ROWS($A$28:$A35),Matriz!$AH$2:$AH$60,0)),"") -> 2 | G35: =IFERROR($E35/12,0) -> 0.25 | I35: Open Access declarado | K35: =COUNTIF(Periódicos!$K$2:$K$168,"Open Access*") -> 40
A36: =IFERROR(INDEX(Matriz!$C$2:$C$60,MATCH(ROWS($A$28:$A36),Matriz!$AH$2:$AH$60,0)),"") -> Resolvendo equação polinomial de quarta ordem e demonstrando um teorema de redução de ordem | D36: =IFERROR(INDEX(Matriz!$B$2:$B$60,MATCH(ROWS($A$28:$A36),Matriz!$AH$2:$AH$60,0)),"") -> Álgebra | E36: =IFERROR(INDEX(Matriz!$AE$2:$AE$60,MATCH(ROWS($A$28:$A36),Matriz!$AH$2:$AH$60,0)),"") -> 2 | F36: =IFERROR(INDEX(Matriz!$AF$2:$AF$60,MATCH(ROWS($A$28:$A36),Matriz!$AH$2:$AH$60,0)),"") -> 1 | G36: =IFERROR($E36/12,0) -> 0.16666667 | I36: Artigos planejados (Journal) | K36: =$H$13 -> 8
A37: =IFERROR(INDEX(Matriz!$C$2:$C$60,MATCH(ROWS($A$28:$A37),Matriz!$AH$2:$AH$60,0)),"") -> Resolvendo (polinômios): x³ + px + q é divisível por (x-a)², encontre a relação entre p e q. | D37: =IFERROR(INDEX(Matriz!$B$2:$B$60,MATCH(ROWS($A$28:$A37),Matriz!$AH$2:$AH$60,0)),"") -> Álgebra | E37: =IFERROR(INDEX(Matriz!$AE$2:$AE$60,MATCH(ROWS($A$28:$A37),Matriz!$AH$2:$AH$60,0)),"") -> 2 | F37: =IFERROR(INDEX(Matriz!$AF$2:$AF$60,MATCH(ROWS($A$28:$A37),Matriz!$AH$2:$AH$60,0)),"") -> 1 | G37: =IFERROR($E37/12,0) -> 0.16666667 | I37: Artigos com link (Journal) | K37: =$I$13 -> 8
A39: QUALIDADE DOS DADOS (itens a corrigir)
A40: Verificação | E40: Ocorrências
A41: Saídas marcadas como concluídas sem link | E41: =SUM(Matriz!$AI$2:$AI$60) -> 52
A42: Links registrados sem marcação de canal | E42: =SUM(Matriz!$AJ$2:$AJ$60) -> 0
A43: Projetos sem tema atribuído | E43: =COUNTIFS(Matriz!$C$2:$C$60,"<>",Matriz!$B$2:$B$60,"") -> 0
A44: Projetos em que o campo Saídas difere da soma dos canais | E44: =SUM(Matriz!$AK$2:$AK$60) -> 40
A45: Linhas com Saídas preenchidas sem título de projeto | E45: =COUNTIFS(Matriz!$C$2:$C$60,"",Matriz!$E$2:$E$60,">0") -> 12
A46: Temas com grafia divergente (ex.: "algebra" vs "Álgebra") | E46: =$C$13 -> 1
A47: Periódicos sem Impact Factor | E47: =COUNTIFS(Periódicos!$A$2:$A$168,"<>",Periódicos!$D$2:$D$168,"") -> 0

Sheet Matriz
A1: ID | B1: Tema | C1: Título YouTube/Ideia | D1: Descrição | E1: Saídas | F1: arXiv/SSRN | G1: Journal | H1: Research Gate | I1: YouTube | J1: TikTok | K1: LinkedIn | L1: Newsletter LinkedIn | M1: Substack | N1: GitHub | O1: Oz.io | P1: Oz Site | Q1: Curso | R1: arXiv/SSRN (link) | S1: Journal (link) | T1: Research Gate (link) | U1: YouTube (link) | V1: TikTok (link) | W1: LinkedIn (link) | X1: Newsletter LinkedIn (link) | Y1: Substack (link) | Z1: GitHub (link) | AA1: Oz.io (link) | AB1: Oz Site (link) | AC1: Curso (link) | AE1: Saídas concluídas (soma canais) | AF1: Links registrados | AG1: Chave ordenação | AH1: Rank | AI1: Concluídas sem link | AJ1: Links sem marcação | AK1: Divergência campo Saídas
A2: 1 | B2: Álgebra | C2: Resolvendo equação polinomial de quarta ordem e demonstrando um teorema de redução de ordem | D2: Neste primeiro vídeo da série sobre raciocínio matemático: resolvo uma equação polinomial do quarto grau para um caso particular e desenvolvo um algoritmo para reduzir o grau desse polinômio pela metade através de uma substituição de variáveis. | E2: 1 | F2: 0 | G2: 0 | H2: 0 | I2: 1 | J2: 1 | K2: 0 | L2: 0 | M2: 0 | N2: 0 | O2: 0 | P2: 0 | Q2: 0 | R2: ------- | S2: ------- | T2: ------- | U2: https://www.youtube.com/watch?v=jdkhDn97CMA | V2: ------- | W2: ------- | X2: ------- | Y2: ------- | Z2: ------- | AA2: ------- | AB2: ------- | AC2: ------- | AE2: =IF($C2="","",SUM($F2:$Q2)) -> 2 | AF2: =IF($C2="","",COUNTIF($R2:$AC2,"http*")) -> 1 | AG2: =IF($C2="","",$AE2*1000+(1000-$A2)) -> 2999 | AH2: =IF($C2="","",RANK($AG2,$AG$2:$AG$60)) -> 9 | AI2: =IF($C2="","",MAX(0,$AE2-$AF2)) -> 1 | AJ2: =IF($C2="","",MAX(0,$AF2-$AE2)) -> 0 | AK2: =IF($C2="","",IF($E2<>$AE2,1,0)) -> 1
A3: 2 | B3: Álgebra | C3: Resolvendo (polinômios): x³ + px + q é divisível por (x-a)², encontre a relação entre p e q. | D3: Resolvendo o seguinte problema: f(x) = x³ + px + q é divisível por (x-a)² Encontre a relação entre p e q. | E3: 1 | F3: 0 | G3: 0 | H3: 0 | I3: 1 | J3: 1 | K3: 0 | L3: 0 | M3: 0 | N3: 0 | O3: 0 | P3: 0 | Q3: 0 | R3: ------- | S3: ------- | T3: ------- | U3: https://www.youtube.com/watch?v=RDFBAXc1P9E | V3: ------- | W3: ------- | X3: ------- | Y3: ------- | Z3: ------- | AA3: ------- | AB3: ------- | AC3: ------- | AE3: =IF($C3="","",SUM($F3:$Q3)) -> 2 | AF3: =IF($C3="","",COUNTIF($R3:$AC3,"http*")) -> 1 | AG3: =IF($C3="","",$AE3*1000+(1000-$A3)) -> 2998 | AH3: =IF($C3="","",RANK($AG3,$AG$2:$AG$60)) -> 10 | AI3: =IF($C3="","",MAX(0,$AE3-$AF3)) -> 1 | AJ3: =IF($C3="","",MAX(0,$AF3-$AE3)) -> 0 | AK3: =IF($C3="","",IF($E3<>$AE3,1,0)) -> 1
A4: 3 | B4: Análise de dados | C4: Como visualizar dados longitudinais: linhas, heatmaps e painéis | D4: Neste vídeo, há uma apresentação com alguns exemplos de gráficos para visualizar dados em painel (dados longitudinais). Arquivo pdf com a aula: https://github.com/ozsp12/ai_data_citizen/blob/main/dados_em_painel/tipos_graficos_dados_em_painel.pdf 00:00 Introdução – Importância das visualizações 00:40 Tipos de gráficos e estrutura do exemplo 01:09 Boas práticas e considerações de design 01:55 Gráfico de barras por mês do ano 02:57 Gráfico de barras empilhado 03:32 Gráfico de barras por produto 04:03 Gráfico de área 04:25 Gráfico de linha 04:51 Mapa de calor (Heatmap) | E4: 1 | F4: 0 | G4: 0 | H4: 0 | I4: 1 | J4: 1 | K4: 0 | L4: 0 | M4: 0 | N4: 0 | O4: 0 | P4: 0 | Q4: 0 | R4: ------- | S4: ------- | T4: ------- | U4: https://www.youtube.com/watch?v=Etwy8F1cmzA | V4: ------- | W4: ------- | X4: ------- | Y4: ------- | Z4: ------- | AA4: ------- | AB4: ------- | AC4: ------- | AE4: =IF($C4="","",SUM($F4:$Q4)) -> 2 | AF4: =IF($C4="","",COUNTIF($R4:$AC4,"http*")) -> 1 | AG4: =IF($C4="","",$AE4*1000+(1000-$A4)) -> 2997 | AH4: =IF($C4="","",RANK($AG4,$AG$2:$AG$60)) -> 11 | AI4: =IF($C4="","",MAX(0,$AE4-$AF4)) -> 1 | AJ4: =IF($C4="","",MAX(0,$AF4-$AE4)) -> 0 | AK4: =IF($C4="","",IF($E4<>$AE4,1,0)) -> 1
A5: 4 | B5: Análise de dados | C5: "Quick and dirty": análise de dados com Python - Precificação e elasticidade. | D5: Neste vídeo, inicio uma série que vou chamar de “Quick and Dirty”, na qual apresento ferramentas de análise de dados para responder rapidamente a perguntas de negócio, usando modelos matemáticos e estatísticos de forma menos rigorosa. A famosa regra 80–20 entre rigor e valor gerado: 20% de rigor e 80% de valor gerado. Como prometido, além de ensinar Python, vou procurar compartilhar algumas ferramentas matemáticas, estatísticas e de análise de dados que conheço, bem como conceitos teóricos de diversas áreas, como microeconomia, macroeconomia, séries temporais, pesquisa operacional, entre outras. Jupyter Notebook: https://github.com/ozsp12/ai_data_citizen/tree/main/quick_dirty_analytics GitHub (Introdução à Programação): https://github.com/ozsp12/programacao_introducao/tree/main | E5: 1 | F5: 0 | G5: 0 | H5: 0 | I5: 1 | J5: 1 | K5: 0 | L5: 0 | M5: 0 | N5: 0 | O5: 0 | P5: 0 | Q5: 0 | R5: ------- | S5: ------- | T5: ------- | U5: https://www.youtube.com/watch?v=Vn45DCpdXNw | V5: ------- | W5: ------- | X5: ------- | Y5: ------- | Z5: ------- | AA5: ------- | AB5: ------- | AC5: ------- | AE5: =IF($C5="","",SUM($F5:$Q5)) -> 2 | AF5: =IF($C5="","",COUNTIF($R5:$AC5,"http*")) -> 1 | AG5: =IF($C5="","",$AE5*1000+(1000-$A5)) -> 2996 | AH5: =IF($C5="","",RANK($AG5,$AG$2:$AG$60)) -> 12 | AI5: =IF($C5="","",MAX(0,$AE5-$AF5)) -> 1 | AJ5: =IF($C5="","",MAX(0,$AF5-$AE5)) -> 0 | AK5: =IF($C5="","",IF($E5<>$AE5,1,0)) -> 1
A6: 5 | B6: Análise de dados | C6: Aula "trilha rápida do analista de dados": exemplos de funções (Python, SQL e DAX) muito utilizadas. | D6: Neste vídeo, eu ensino como utilizar algumas funções de Python, SQL e DAX (Power BI), úteis e amplamente utilizadas no dia a dia de um analista de dados. A ideia é proporcionar uma aula para que cidadãos dos dados se familiarizem com a linguagem de programação de alto nível, a manipulação de dados, os bancos de dados e as visualizações. Link do Notebook e PBIX no GitHub: https://github.com/ozsp12/ai_data_citizen/tree/main/fast_track SQL: SELECT FROM WHERE ORDER BY SUM(), COUNT(), AVG() GROUP BY CREATE, INSERT, DELETE Python (pandas): import pandas as pd pd.read_csv() df.head() df.tail() df.info() df.describe() df['coluna'] df[df['coluna'] "maior que" x] df.groupby() df.sort_values() df.isnull().sum() df.fillna() df.dropna() DAX (Power BI): CALCULATE() FILTER() ALL() SUM() COUNT() DIVIDE() IF() SWITCH() VALUES() RELATED() | E6: 1 | F6: 0 | G6: 0 | H6: 0 | I6: 1 | J6: 1 | K6: 0 | L6: 0 | M6: 0 | N6: 0 | O6: 0 | P6: 0 | Q6: 0 | R6: ------- | S6: ------- | T6: ------- | U6: https://www.youtube.com/watch?v=dLDmXewxwpA | V6: ------- | W6: ------- | X6: ------- | Y6: ------- | Z6: ------- | AA6: ------- | AB6: ------- | AC6: ------- | AE6: =IF($C6="","",SUM($F6:$Q6)) -> 2 | AF6: =IF($C6="","",COUNTIF($R6:$AC6,"http*")) -> 1 | AG6: =IF($C6="","",$AE6*1000+(1000-$A6)) -> 2995 | AH6: =IF($C6="","",RANK($AG6,$AG$2:$AG$60)) -> 13 | AI6: =IF($C6="","",MAX(0,$AE6-$AF6)) -> 1 | AJ6: =IF($C6="","",MAX(0,$AF6-$AE6)) -> 0 | AK6: =IF($C6="","",IF($E6<>$AE6,1,0)) -> 1
A7: 6 | B7: Análise matemática | C7: Derivative of the exponential function via the limit definition | D7: In this video, we derive the exponential function from first principles using the limit definition of the derivative. Starting with $f(x)=a^x$, we examine the increment of the function, reorganize the expression algebraically, and obtain the derivative step by step in a clear and rigorous way. This derivation is a classic result of differential calculus and helps deepen understanding of exponential functions and their role in mathematics. This video is intended for students and anyone interested in: calculus, limits, derivatives, exponential functions, and mathematical reasoning. References [1] Stewart, J. Calculus: Early Transcendentals. 8th ed., Cengage Learning, 2016. [2] Hass, J. R., Heil, C. E., Weir, M. D., and Bogacki, P. Thomas’ Calculus: Early Transcendentals, SI Units. 15th ed., Pearson, 2023. [3] Spivak, M. Calculus. 4th ed., Publish or Perish, Inc., 2008. [4] Apostol, T. M. Calculus, Volume 1: One-Variable Calculus, with an Introduction to Linear Algebra. 2nd ed., John Wiley & Sons, 1991. [5] Strang, G. Calculus. 2nd ed., Wellesley-Cambridge Press, 2010. #Calculus #Derivative #ExponentialFunction #Mathematics #Limits #MathEducation | E7: 1 | F7: 0 | G7: 0 | H7: 0 | I7: 1 | J7: 1 | K7: 0 | L7: 0 | M7: 0 | N7: 0 | O7: 0 | P7: 0 | Q7: 0 | R7: ------- | S7: ------- | T7: ------- | U7: https://www.youtube.com/watch?v=RBGLS71u6wI | V7: ------- | W7: ------- | X7: ------- | Y7: ------- | Z7: ------- | AA7: ------- | AB7: ------- | AC7: ------- | AE7: =IF($C7="","",SUM($F7:$Q7)) -> 2 | AF7: =IF($C7="","",COUNTIF($R7:$AC7,"http*")) -> 1 | AG7: =IF($C7="","",$AE7*1000+(1000-$A7)) -> 2994 | AH7: =IF($C7="","",RANK($AG7,$AG$2:$AG$60)) -> 14 | AI7: =IF($C7="","",MAX(0,$AE7-$AF7)) -> 1 | AJ7: =IF($C7="","",MAX(0,$AF7-$AE7)) -> 0 | AK7: =IF($C7="","",IF($E7<>$AE7,1,0)) -> 1
A8: 7 | B8: Análise matemática | C8: Why the Gradient Is Orthogonal to Level Surfaces | D8: In this video, I present a visual explanation of the relationship between linear algebra and differential calculus: vectors orthogonal to the same nonzero vector lie in the same plane. In R³, given a non-zero vector c, the set of all vectors x such that the inner product between x and c is equal to zero forms a two-dimensional vector subspace. Geometrically, this subspace is a plane perpendicular to the vector c. Thus, if three vectors u, v, and w simultaneously satisfy: [u , c] = 0, [v , c] = 0, [w , c] = 0. where [ , ] denotes the usual inner product. Then all three belong to the same plane, perpendicular to c. Since this plane has dimension 2, three vectors contained in it cannot be linearly independent. Therefore, u, v, and w are necessarily linearly dependent. This idea arises naturally in geometry and differential calculus. When we have a level surface, that is, a surface defined by the points at which a function g(x, y, z) assumes a constant value, any curve contained in that surface preserves this value along its path. By differentiating this condition using the chain rule, we obtain that the inner product between the gradient of g and the tangent vector to the curve is zero. In other words, the tangent vector to the curve is orthogonal to the gradient of the function. Hence, the gradient points in the normal direction to the level surface. At the intersection of two level surfaces, the intersection curve has a tangent vector that is simultaneously orthogonal to both gradients. For this reason, this tangent vector is parallel to the cross product of the gradients of the two functions. References [1] Apostol, T. M. (1969). Calculus, Volume II: Multi-variable calculus and linear algebra, with applications to differential equations and probability (2nd ed.). John Wiley & Sons. [2] Axler, S. (2015). Linear algebra done right (3rd ed.). Springer. [3] do Carmo, M. P. (1976). Differential geometry of curves and surfaces. Prentice-Hall. [4] Hoffman, K., & Kunze, R. (1971). Linear algebra (2nd ed.). Prentice-Hall. [5] Lee, J. M. (2013). Introduction to smooth manifolds (2nd ed.). Springer. [6] Marsden, J. E., & Tromba, A. J. (2003). Vector calculus (5th ed.). W. H. Freeman. [7] Spivak, M. (1965). Calculus on manifolds: A modern approach to classical theorems of advanced calculus. W. A. Benjamin. [8] Strang, G. (2016). Introduction to linear algebra (5th ed.). Wellesley-Cambridge Press. | E8: 1 | F8: 0 | G8: 0 | H8: 0 | I8: 1 | J8: 1 | K8: 0 | L8: 0 | M8: 0 | N8: 0 | O8: 0 | P8: 0 | Q8: 0 | R8: ------- | S8: ------- | T8: ------- | U8: https://www.youtube.com/watch?v=E-RCxwW9PBw | V8: ------- | W8: ------- | X8: ------- | Y8: ------- | Z8: ------- | AA8: ------- | AB8: ------- | AC8: ------- | AE8: =IF($C8="","",SUM($F8:$Q8)) -> 2 | AF8: =IF($C8="","",COUNTIF($R8:$AC8,"http*")) -> 1 | AG8: =IF($C8="","",$AE8*1000+(1000-$A8)) -> 2993 | AH8: =IF($C8="","",RANK($AG8,$AG$2:$AG$60)) -> 15 | AI8: =IF($C8="","",MAX(0,$AE8-$AF8)) -> 1 | AJ8: =IF($C8="","",MAX(0,$AF8-$AE8)) -> 0 | AK8: =IF($C8="","",IF($E8<>$AE8,1,0)) -> 1
A9: 8 | B9: Análise matemática | C9: Por que o gradiente é perpendicular às superfícies de nível? | D9: Neste vídeo, organizei uma explicação visual sobre a relação entre álgebra linear e cálculo diferencial: vetores ortogonais a um mesmo vetor não nulo pertencem ao mesmo plano. Em R³, dado um vetor c não nulo, o conjunto de todos os vetores x tais que o produto escalar entre x e c é igual a zero forma um subespaço vetorial de dimensão 2. Geometricamente, esse subespaço é um plano perpendicular ao vetor c. Assim, se três vetores u, v e w satisfazem simultaneamente: [u , c] = 0, [v , c] = 0, [w , c] = 0. Sendo [ , ] o produto escalar usual. Então, os três pertencem ao mesmo plano, perpendicular a c. Como esse plano tem dimensão 2, três vetores nele não podem ser linearmente independentes. Portanto, u, v e w são necessariamente linearmente dependentes. Essa ideia surge naturalmente na geometria e no cálculo diferencial. Quando temos uma superfície de nível, isto é, uma superfície definida pelos pontos em que uma função g(x, y, z) assume um valor constante, qualquer curva contida nessa superfície mantém esse valor ao longo de seu trajeto. Ao derivar essa condição pela regra da cadeia, obtemos que o produto escalar entre o gradiente de g e o vetor tangente à curva é nulo. Em outras palavras, o vetor tangente à curva é ortogonal ao gradiente da função. Logo, o gradiente aponta na direção normal à superfície de nível. No caso da interseção de duas superfícies de nível, a curva de interseção possui um vetor tangente que é simultaneamente ortogonal a ambos os gradientes. Por isso, esse vetor tangente é paralelo ao produto vetorial dos gradientes das duas funções. Referências [1] Apostol, T. M. (1969). Calculus, Volume II: Multi-variable calculus and linear algebra, with applications to differential equations and probability (2nd ed.). John Wiley & Sons. [2] Axler, S. (2015). Linear algebra done right (3rd ed.). Springer. [3] do Carmo, M. P. (1976). Differential geometry of curves and surfaces. Prentice-Hall. [4] Hoffman, K., & Kunze, R. (1971). Linear algebra (2nd ed.). Prentice-Hall. [5] Lee, J. M. (2013). Introduction to smooth manifolds (2nd ed.). Springer. [6] Marsden, J. E., & Tromba, A. J. (2003). Vector calculus (5th ed.). W. H. Freeman. [7] Spivak, M. (1965). Calculus on manifolds: A modern approach to classical theorems of advanced calculus. W. A. Benjamin. [8] Strang, G. (2016). Introduction to linear algebra (5th ed.). Wellesley-Cambridge Press. | E9: 1 | F9: 0 | G9: 0 | H9: 0 | I9: 1 | J9: 1 | K9: 0 | L9: 0 | M9: 0 | N9: 0 | O9: 0 | P9: 0 | Q9: 0 | R9: ------- | S9: ------- | T9: ------- | U9: https://www.youtube.com/watch?v=jMSWzqKGbBs | V9: ------- | W9: ------- | X9: ------- | Y9: ------- | Z9: ------- | AA9: ------- | AB9: ------- | AC9: ------- | AE9: =IF($C9="","",SUM($F9:$Q9)) -> 2 | AF9: =IF($C9="","",COUNTIF($R9:$AC9,"http*")) -> 1 | AG9: =IF($C9="","",$AE9*1000+(1000-$A9)) -> 2992 | AH9: =IF($C9="","",RANK($AG9,$AG$2:$AG$60)) -> 16 | AI9: =IF($C9="","",MAX(0,$AE9-$AF9)) -> 1 | AJ9: =IF($C9="","",MAX(0,$AF9-$AE9)) -> 0 | AK9: =IF($C9="","",IF($E9<>$AE9,1,0)) -> 1
A10: 9 | B10: Análise matemática | C10: Benderama: banach-tarski machine and quantum Bender. Explanation of the harmonic series divergence. | D10: Neste vídeo, uso o episódio 17 da sexta temporada de Futurama, “Benderama”, para explicar a série harmônica e demonstrar por que ela é divergente. No episódio, o Professor Farnsworth apresenta uma expressão matemática para calcular a massa total acumulada dos Benders ao longo de sucessivos processos de duplicação. Embora a massa individual de cada cópia diminua rapidamente, o número de Benders cresce exponencialmente. Ao simplificar a expressão, obtém-se a série harmônica, cuja soma cresce indefinidamente. 00:00 Introdução: matemática em *Futurama* 00:26 Trecho do episódio “Benderama” 01:39 O paradoxo de Banach–Tarski e a premissa do episódio 04:20 A equação apresentada pelo Professor Farnsworth 06:29 Dedução da massa dos Benders 13:47 Da soma das massas à série harmônica 15:29 Por que a série é divergente 17:09 Número de Benders, massa individual e efeitos subatômicos 20:22 Encerramento link para apresentação do vídeo e para o notebook Jupyter com o código que gera os gráficos apresentados no vídeo: https://github.com/ozsp12/math_elementary/tree/main/futurama_banach_tarski Referências 1. OpenStax, Calculus, Volume 2 (OpenStax, Rice University, Houston, 2016), Secs. 5.2–5.3. 2. S. Abbott, Understanding Analysis, 2nd ed. (Springer, New York, 2015). 3. T. M. Apostol, Mathematical Analysis: A Modern Approach to Advanced Calculus, 2nd ed. (Addison-Wesley, Reading, MA, 1974). 4. W. Rudin, Principles of Mathematical Analysis, 3rd ed. (McGraw-Hill, New York, 1976). 5. G. B. Folland, Real Analysis: Modern Techniques and Their Applications, 2nd ed. (Wiley, New York, 1999). 6. G. Tomkowicz and S. Wagon, The Banach–Tarski Paradox, 2nd ed. (Cambridge University Press, Cambridge, 2016). 7. S. Banach and A. Tarski, “Sur la décomposition des ensembles de points en parties respectivement congruentes,” Fund. Math. 6, 244–277 (1924). 8. K. Buchhorn, “The Banach–Tarski Paradox,” arXiv:2108.05714 (2021). 9. S. Singh, Os Segredos Matemáticos dos Simpsons (Record, Rio de Janeiro, 2016). | E10: 1 | F10: 0 | G10: 0 | H10: 0 | I10: 1 | J10: 1 | K10: 0 | L10: 0 | M10: 0 | N10: 0 | O10: 0 | P10: 0 | Q10: 0 | R10: ------- | S10: ------- | T10: ------- | U10: https://www.youtube.com/watch?v=zb1tEaJ2yFc | V10: ------- | W10: ------- | X10: ------- | Y10: ------- | Z10: ------- | AA10: ------- | AB10: ------- | AC10: ------- | AE10: =IF($C10="","",SUM($F10:$Q10)) -> 2 | AF10: =IF($C10="","",COUNTIF($R10:$AC10,"http*")) -> 1 | AG10: =IF($C10="","",$AE10*1000+(1000-$A10)) -> 2991 | AH10: =IF($C10="","",RANK($AG10,$AG$2:$AG$60)) -> 17 | AI10: =IF($C10="","",MAX(0,$AE10-$AF10)) -> 1 | AJ10: =IF($C10="","",MAX(0,$AF10-$AE10)) -> 0 | AK10: =IF($C10="","",IF($E10<>$AE10,1,0)) -> 1
A11: 10 | B11: Análise matemática | C11: Questão Dissertativa do IME de 2026: uma demonstração que engana muita gente. Desafiadora! | D11: Neste vídeo, resolvo a questão 8 do segundo dia do exame do IME 2025/2026. A questão parece desafiadora, mas, na verdade, é bastante simples; ainda assim, ela esconde vários conceitos interessantes, que são discutidos ao longo do vídeo. Como o teorema do ponto fixo de Banach (1922). Exames do IME https://inscricoes.ime.eb.br/cfg/ Link para a prova de Matemática do IME https://inscricoes.ime.eb.br/documentos/Prova_Discursiva_de_Matem%C3%A1tica.pdf Link para paper pedagógico sobre a resolução (em inglês) https://papers.ssrn.com/sol3/papers.cfm?abstract_id=6779078 0:00 Introdução e apresentação da questão 0:19 Enunciado do problema 0:30 Por que a questão parece mais difícil do que é 2:31 Definição do seno hiperbólico 3:15 Resolvendo a equação para obter o arco-seno hiperbólico 6:24 Identificação da expressão logarítmica 7:29 Reescrevendo o sistema com uma função auxiliar 9:16 Ideia de ponto fixo 11:17 Interpretação por sequência iterativa 13:19 Consequência: x = y = z 14:35 Prova da unicidade da solução 17:35 Demonstração por contradição 20:34 Comentário final sobre o valor conceitual da questão 22:00 Encerramento | E11: 1 | F11: 0 | G11: 0 | H11: 0 | I11: 1 | J11: 1 | K11: 0 | L11: 0 | M11: 0 | N11: 0 | O11: 0 | P11: 0 | Q11: 0 | R11: ------- | S11: ------- | T11: ------- | U11: https://www.youtube.com/watch?v=oY2PUGaeMuw | V11: ------- | W11: ------- | X11: ------- | Y11: ------- | Z11: ------- | AA11: ------- | AB11: ------- | AC11: ------- | AE11: =IF($C11="","",SUM($F11:$Q11)) -> 2 | AF11: =IF($C11="","",COUNTIF($R11:$AC11,"http*")) -> 1 | AG11: =IF($C11="","",$AE11*1000+(1000-$A11)) -> 2990 | AH11: =IF($C11="","",RANK($AG11,$AG$2:$AG$60)) -> 18 | AI11: =IF($C11="","",MAX(0,$AE11-$AF11)) -> 1 | AJ11: =IF($C11="","",MAX(0,$AF11-$AE11)) -> 0 | AK11: =IF($C11="","",IF($E11<>$AE11,1,0)) -> 1
A12: 11 | B12: Análise matemática | C12: Desigualdade de Cauchy–Schwarz: uma demonstração simples para estudantes avançados do ensino médio. | D12: Neste vídeo, demonstro a desigualdade de Cauchy–Schwarz em um contexto de análise real e sob a perspectiva da teoria dos números, sem recorrer a conceitos de espaços métricos e de normas. A demonstração é acessível a estudantes avançados do ensino médio. | E12: 1 | F12: 0 | G12: 0 | H12: 0 | I12: 1 | J12: 1 | K12: 0 | L12: 0 | M12: 0 | N12: 0 | O12: 0 | P12: 0 | Q12: 0 | R12: ------- | S12: ------- | T12: ------- | U12: https://www.youtube.com/watch?v=5UVnLilScIg | V12: ------- | W12: ------- | X12: ------- | Y12: ------- | Z12: ------- | AA12: ------- | AB12: ------- | AC12: ------- | AE12: =IF($C12="","",SUM($F12:$Q12)) -> 2 | AF12: =IF($C12="","",COUNTIF($R12:$AC12,"http*")) -> 1 | AG12: =IF($C12="","",$AE12*1000+(1000-$A12)) -> 2989 | AH12: =IF($C12="","",RANK($AG12,$AG$2:$AG$60)) -> 19 | AI12: =IF($C12="","",MAX(0,$AE12-$AF12)) -> 1 | AJ12: =IF($C12="","",MAX(0,$AF12-$AE12)) -> 0 | AK12: =IF($C12="","",IF($E12<>$AE12,1,0)) -> 1
A13: 12 | B13: Análise matemática | C13: Demonstração da desigualdade matemática (exercício 2.7 do livro The Cauchy-Schwarz Master Class). | D13: Neste vídeo resolvo o exercício 2.7 do livro Cauchy-Schwarz Master-Class. O enunciado do problema é o seguinte: dados x, y, z ≥ 0: xyz ≥ 1 → (1 + x)(1 + y)(1 + z) ≥ 8. E eu acabo discutindo e generalizando o problema. Parte do vídeo é improvisada, pois fui pensando enquanto gravava e acabei fazendo algumas afirmações sem refletir profundamente, que talvez estejam incorretas ou incompletas. Porém, um dos objetivos do meu canal é demonstrar como pesquisadores profissionais pensam e atacam problemas, mesmo que sejam problemas de fixação de conceitos. Steele, J. M. (2004). The Cauchy-Schwarz Master Class: An Introduction to the Art of Mathematical Inequalities. Cambridge University Press. DOI: https://doi.org/10.1017/CBO9780511817106. https://www.cambridge.org/core/books/cauchyschwarz-master-class/A444E291C6E5928ADB2DD9F37C4C6EB8 | E13: 1 | F13: 0 | G13: 0 | H13: 0 | I13: 1 | J13: 1 | K13: 0 | L13: 0 | M13: 0 | N13: 0 | O13: 0 | P13: 0 | Q13: 0 | R13: ------- | S13: ------- | T13: ------- | U13: https://www.youtube.com/watch?v=MXczcfmpxGY | V13: ------- | W13: ------- | X13: ------- | Y13: ------- | Z13: ------- | AA13: ------- | AB13: ------- | AC13: ------- | AE13: =IF($C13="","",SUM($F13:$Q13)) -> 2 | AF13: =IF($C13="","",COUNTIF($R13:$AC13,"http*")) -> 1 | AG13: =IF($C13="","",$AE13*1000+(1000-$A13)) -> 2988 | AH13: =IF($C13="","",RANK($AG13,$AG$2:$AG$60)) -> 20 | AI13: =IF($C13="","",MAX(0,$AE13-$AF13)) -> 1 | AJ13: =IF($C13="","",MAX(0,$AF13-$AE13)) -> 0 | AK13: =IF($C13="","",IF($E13<>$AE13,1,0)) -> 1
... A48: 47 | B48: algebra | C48: 10th-degree polynomial equation | D48: 10th-degree polynomial equation | E48: 1 | F48: 0 | G48: 0 | H48: 0 | I48: 1 | J48: 1 | K48: 0 | L48: 0 | M48: 0 | N48: 0 | O48: 0 | P48: 0 | Q48: 0 | R48: ------- | S48: ------- | T48: ------- | U48: https://www.youtube.com/watch?v=mJsv_uLeNgU | V48: ------- | W48: ------- | X48: ------- | Y48: ------- | Z48: ------- | AA48: ------- | AB48: ------- | AC48: ------- | AE48: =IF($C48="","",SUM($F48:$Q48)) -> 2 | AF48: =IF($C48="","",COUNTIF($R48:$AC48,"http*")) -> 1 | AG48: =IF($C48="","",$AE48*1000+(1000-$A48)) -> 2953 | AH48: =IF($C48="","",RANK($AG48,$AG$2:$AG$60)) -> 47 | AI48: =IF($C48="","",MAX(0,$AE48-$AF48)) -> 1 | AJ48: =IF($C48="","",MAX(0,$AF48-$AE48)) -> 0 | AK48: =IF($C48="","",IF($E48<>$AE48,1,0)) -> 1
A49: 48 | E49: 1 | F49: 0 | G49: 0 | H49: 0 | I49: 0 | J49: 0 | K49: 0 | L49: 0 | M49: 0 | N49: 0 | O49: 0 | P49: 0 | Q49: 0 | R49: ------- | S49: ------- | T49: ------- | U49: ------- | V49: ------- | W49: ------- | X49: ------- | Y49: ------- | Z49: ------- | AA49: ------- | AB49: ------- | AC49: ------- | AE49: =IF($C49="","",SUM($F49:$Q49)) | AF49: =IF($C49="","",COUNTIF($R49:$AC49,"http*")) | AG49: =IF($C49="","",$AE49*1000+(1000-$A49)) | AH49: =IF($C49="","",RANK($AG49,$AG$2:$AG$60)) | AI49: =IF($C49="","",MAX(0,$AE49-$AF49)) | AJ49: =IF($C49="","",MAX(0,$AF49-$AE49)) | AK49: =IF($C49="","",IF($E49<>$AE49,1,0))
A50: 49 | E50: 1 | F50: 0 | G50: 0 | H50: 0 | I50: 0 | J50: 0 | K50: 0 | L50: 0 | M50: 0 | N50: 0 | O50: 0 | P50: 0 | Q50: 0 | R50: ------- | S50: ------- | T50: ------- | U50: ------- | V50: ------- | W50: ------- | X50: ------- | Y50: ------- | Z50: ------- | AA50: ------- | AB50: ------- | AC50: ------- | AE50: =IF($C50="","",SUM($F50:$Q50)) | AF50: =IF($C50="","",COUNTIF($R50:$AC50,"http*")) | AG50: =IF($C50="","",$AE50*1000+(1000-$A50)) | AH50: =IF($C50="","",RANK($AG50,$AG$2:$AG$60)) | AI50: =IF($C50="","",MAX(0,$AE50-$AF50)) | AJ50: =IF($C50="","",MAX(0,$AF50-$AE50)) | AK50: =IF($C50="","",IF($E50<>$AE50,1,0))
A51: 50 | E51: 1 | F51: 0 | G51: 0 | H51: 0 | I51: 0 | J51: 0 | K51: 0 | L51: 0 | M51: 0 | N51: 0 | O51: 0 | P51: 0 | Q51: 0 | R51: ------- | S51: ------- | T51: ------- | U51: ------- | V51: ------- | W51: ------- | X51: ------- | Y51: ------- | Z51: ------- | AA51: ------- | AB51: ------- | AC51: ------- | AE51: =IF($C51="","",SUM($F51:$Q51)) | AF51: =IF($C51="","",COUNTIF($R51:$AC51,"http*")) | AG51: =IF($C51="","",$AE51*1000+(1000-$A51)) | AH51: =IF($C51="","",RANK($AG51,$AG$2:$AG$60)) | AI51: =IF($C51="","",MAX(0,$AE51-$AF51)) | AJ51: =IF($C51="","",MAX(0,$AF51-$AE51)) | AK51: =IF($C51="","",IF($E51<>$AE51,1,0))
A52: 51 | E52: 1 | F52: 0 | G52: 0 | H52: 0 | I52: 0 | J52: 0 | K52: 0 | L52: 0 | M52: 0 | N52: 0 | O52: 0 | P52: 0 | Q52: 0 | R52: ------- | S52: ------- | T52: ------- | U52: ------- | V52: ------- | W52: ------- | X52: ------- | Y52: ------- | Z52: ------- | AA52: ------- | AB52: ------- | AC52: ------- | AE52: =IF($C52="","",SUM($F52:$Q52)) | AF52: =IF($C52="","",COUNTIF($R52:$AC52,"http*")) | AG52: =IF($C52="","",$AE52*1000+(1000-$A52)) | AH52: =IF($C52="","",RANK($AG52,$AG$2:$AG$60)) | AI52: =IF($C52="","",MAX(0,$AE52-$AF52)) | AJ52: =IF($C52="","",MAX(0,$AF52-$AE52)) | AK52: =IF($C52="","",IF($E52<>$AE52,1,0))
A53: 52 | E53: 1 | F53: 0 | G53: 0 | H53: 0 | I53: 0 | J53: 0 | K53: 0 | L53: 0 | M53: 0 | N53: 0 | O53: 0 | P53: 0 | Q53: 0 | R53: ------- | S53: ------- | T53: ------- | U53: ------- | V53: ------- | W53: ------- | X53: ------- | Y53: ------- | Z53: ------- | AA53: ------- | AB53: ------- | AC53: ------- | AE53: =IF($C53="","",SUM($F53:$Q53)) | AF53: =IF($C53="","",COUNTIF($R53:$AC53,"http*")) | AG53: =IF($C53="","",$AE53*1000+(1000-$A53)) | AH53: =IF($C53="","",RANK($AG53,$AG$2:$AG$60)) | AI53: =IF($C53="","",MAX(0,$AE53-$AF53)) | AJ53: =IF($C53="","",MAX(0,$AF53-$AE53)) | AK53: =IF($C53="","",IF($E53<>$AE53,1,0))
A54: 53 | E54: 1 | F54: 0 | G54: 0 | H54: 0 | I54: 0 | J54: 0 | K54: 0 | L54: 0 | M54: 0 | N54: 0 | O54: 0 | P54: 0 | Q54: 0 | R54: ------- | S54: ------- | T54: ------- | U54: ------- | V54: ------- | W54: ------- | X54: ------- | Y54: ------- | Z54: ------- | AA54: ------- | AB54: ------- | AC54: ------- | AE54: =IF($C54="","",SUM($F54:$Q54)) | AF54: =IF($C54="","",COUNTIF($R54:$AC54,"http*")) | AG54: =IF($C54="","",$AE54*1000+(1000-$A54)) | AH54: =IF($C54="","",RANK($AG54,$AG$2:$AG$60)) | AI54: =IF($C54="","",MAX(0,$AE54-$AF54)) | AJ54: =IF($C54="","",MAX(0,$AF54-$AE54)) | AK54: =IF($C54="","",IF($E54<>$AE54,1,0))
A55: 54 | E55: 1 | F55: 0 | G55: 0 | H55: 0 | I55: 0 | J55: 0 | K55: 0 | L55: 0 | M55: 0 | N55: 0 | O55: 0 | P55: 0 | Q55: 0 | R55: ------- | S55: ------- | T55: ------- | U55: ------- | V55: ------- | W55: ------- | X55: ------- | Y55: ------- | Z55: ------- | AA55: ------- | AB55: ------- | AC55: ------- | AE55: =IF($C55="","",SUM($F55:$Q55)) | AF55: =IF($C55="","",COUNTIF($R55:$AC55,"http*")) | AG55: =IF($C55="","",$AE55*1000+(1000-$A55)) | AH55: =IF($C55="","",RANK($AG55,$AG$2:$AG$60)) | AI55: =IF($C55="","",MAX(0,$AE55-$AF55)) | AJ55: =IF($C55="","",MAX(0,$AF55-$AE55)) | AK55: =IF($C55="","",IF($E55<>$AE55,1,0))
A56: 55 | E56: 1 | F56: 0 | G56: 0 | H56: 0 | I56: 0 | J56: 0 | K56: 0 | L56: 0 | M56: 0 | N56: 0 | O56: 0 | P56: 0 | Q56: 0 | R56: ------- | S56: ------- | T56: ------- | U56: ------- | V56: ------- | W56: ------- | X56: ------- | Y56: ------- | Z56: ------- | AA56: ------- | AB56: ------- | AC56: ------- | AE56: =IF($C56="","",SUM($F56:$Q56)) | AF56: =IF($C56="","",COUNTIF($R56:$AC56,"http*")) | AG56: =IF($C56="","",$AE56*1000+(1000-$A56)) | AH56: =IF($C56="","",RANK($AG56,$AG$2:$AG$60)) | AI56: =IF($C56="","",MAX(0,$AE56-$AF56)) | AJ56: =IF($C56="","",MAX(0,$AF56-$AE56)) | AK56: =IF($C56="","",IF($E56<>$AE56,1,0))
A57: 56 | E57: 1 | F57: 0 | G57: 0 | H57: 0 | I57: 0 | J57: 0 | K57: 0 | L57: 0 | M57: 0 | N57: 0 | O57: 0 | P57: 0 | Q57: 0 | R57: ------- | S57: ------- | T57: ------- | U57: ------- | V57: ------- | W57: ------- | X57: ------- | Y57: ------- | Z57: ------- | AA57: ------- | AB57: ------- | AC57: ------- | AE57: =IF($C57="","",SUM($F57:$Q57)) | AF57: =IF($C57="","",COUNTIF($R57:$AC57,"http*")) | AG57: =IF($C57="","",$AE57*1000+(1000-$A57)) | AH57: =IF($C57="","",RANK($AG57,$AG$2:$AG$60)) | AI57: =IF($C57="","",MAX(0,$AE57-$AF57)) | AJ57: =IF($C57="","",MAX(0,$AF57-$AE57)) | AK57: =IF($C57="","",IF($E57<>$AE57,1,0))
A58: 57 | E58: 1 | F58: 0 | G58: 0 | H58: 0 | I58: 0 | J58: 0 | K58: 0 | L58: 0 | M58: 0 | N58: 0 | O58: 0 | P58: 0 | Q58: 0 | R58: ------- | S58: ------- | T58: ------- | U58: ------- | V58: ------- | W58: ------- | X58: ------- | Y58: ------- | Z58: ------- | AA58: ------- | AB58: ------- | AC58: ------- | AE58: =IF($C58="","",SUM($F58:$Q58)) | AF58: =IF($C58="","",COUNTIF($R58:$AC58,"http*")) | AG58: =IF($C58="","",$AE58*1000+(1000-$A58)) | AH58: =IF($C58="","",RANK($AG58,$AG$2:$AG$60)) | AI58: =IF($C58="","",MAX(0,$AE58-$AF58)) | AJ58: =IF($C58="","",MAX(0,$AF58-$AE58)) | AK58: =IF($C58="","",IF($E58<>$AE58,1,0))
A59: 58 | E59: 1 | F59: 0 | G59: 0 | H59: 0 | I59: 0 | J59: 0 | K59: 0 | L59: 0 | M59: 0 | N59: 0 | O59: 0 | P59: 0 | Q59: 0 | R59: ------- | S59: ------- | T59: ------- | U59: ------- | V59: ------- | W59: ------- | X59: ------- | Y59: ------- | Z59: ------- | AA59: ------- | AB59: ------- | AC59: ------- | AE59: =IF($C59="","",SUM($F59:$Q59)) | AF59: =IF($C59="","",COUNTIF($R59:$AC59,"http*")) | AG59: =IF($C59="","",$AE59*1000+(1000-$A59)) | AH59: =IF($C59="","",RANK($AG59,$AG$2:$AG$60)) | AI59: =IF($C59="","",MAX(0,$AE59-$AF59)) | AJ59: =IF($C59="","",MAX(0,$AF59-$AE59)) | AK59: =IF($C59="","",IF($E59<>$AE59,1,0))
A60: 59 | E60: 1 | F60: 0 | G60: 0 | H60: 0 | I60: 0 | J60: 0 | K60: 0 | L60: 0 | M60: 0 | N60: 0 | O60: 0 | P60: 0 | Q60: 0 | R60: ------- | S60: ------- | T60: ------- | U60: ------- | V60: ------- | W60: ------- | X60: ------- | Y60: ------- | Z60: ------- | AA60: ------- | AB60: ------- | AC60: ------- | AE60: =IF($C60="","",SUM($F60:$Q60)) | AF60: =IF($C60="","",COUNTIF($R60:$AC60,"http*")) | AG60: =IF($C60="","",$AE60*1000+(1000-$A60)) | AH60: =IF($C60="","",RANK($AG60,$AG$2:$AG$60)) | AI60: =IF($C60="","",MAX(0,$AE60-$AF60)) | AJ60: =IF($C60="","",MAX(0,$AF60-$AE60)) | AK60: =IF($C60="","",IF($E60<>$AE60,1,0))

Sheet Periódicos
A1: Nome do periódico | B1: Sigla | C1: Publisher | D1: Impact Factor | E1: Área | F1: Escopo | G1: URL | H1: Exemplo de artigo | I1: Fit com projetos (1–5) | J1: APC | K1: Open Access | L1: Tempo editorial | M1: Observações | N1: Fonte / referência
A2: International Journal of Data Science and Analytics | B2: JDSA | C2: Springer | D2: 2.9 | E2: data science | F2: Data Science has been established as an important emergent scientific field and paradigm driving research evolution in such disciplines as statistics, computing science and intelligence science, and practical transformation in such domains as science, engineering, the public sector, business, social sci­ence, and lifestyle. The field encompasses the larger ar­eas of artificial intelligence, data analytics, machine learning, pattern recognition, natural language understanding, and big data manipulation. It also tackles related new sci­entific chal­lenges, ranging from data capture, creation, storage, retrieval, sharing, analysis, optimization, and vis­ualization, to integrative analysis across heterogeneous and interdependent complex resources for better decision-making, collaboration, and, ultimately, value creation. The International Journal of Data Science and Analytics (JDSA) brings together thought leaders, researchers, industry practitioners, and potential users of data science and analytics, to develop the field, discuss new trends and opportunities, exchange ideas and practices, and promote transdisciplinary and cross-domain collaborations. The jour­nal is composed of three streams: Regular, to communicate original and reproducible theoretical and experimental findings on data science and analytics; Applications, to report the significant data science applications to real-life situations; and Trends, to report expert opinion and comprehensive surveys and reviews of relevant areas and topics in data science and analytics. Topics of relevance include all aspects of the trends, scientific foundations, techniques, and applica­tions of data science and analytics, with a primary focus on: statistical and mathematical foundations for data science and analytics; understanding and analytics of complex data, human, domain, network, organizational, social, behavior, and system characteristics, complexities and intelligences; creation and extraction, processing, representation and modelling, learning and discovery, fusion and integration, presentation and visualization of complex data, behavior, knowledge and intelligence; data analytics, pattern recognition, knowledge discovery, machine learning, deep analytics and deep learning, and intelligent processing of various data (including transaction, text, image, video, graph and network), behaviors and systems; active, real-time, personalized, actionable and automated analytics, learning, computation, optimization, presentation and recommendation; big data architecture, infrastructure, computing, matching, indexing, query processing, mapping, search, retrieval, interopera­bility, exchange, and recommendation; in-memory, distributed, parallel, scalable and high-performance computing, analytics and optimization for big data; review, surveys, trends, prospects and opportunities of data science research, innovation and applications; data science applications, intelligent devices and services in scientific, business, governmental, cultural, behavioral, social and economic, health and medical, human, natural and artificial (including online/Web, cloud, IoT, mobile and social media) domains; and ethics, quality, privacy, safety and security, trust, and risk of data science and analytics | G2: https://link.springer.com/journal/41060 | H2: https://doi.org/10.1007/s41060-023-00454-0 | I2: 5 | J2: Consultar política atual | K2: Híbrido/consultar | L2: 18 dias (mediana até 1ª decisão) | M2: APC deve ser conferido antes da submissão. | N2: https://link.springer.com/journal/41060
A3: Advances in Theoretical and Mathematical Physics | B3: ATMP | C3: International Press | D3: 1 | E3: física | F3: Pesquisa original em física teórica e matemática, especialmente em temas na interface entre física e matemática. | G3: https://intlpress.com/site/pub/pages/journals/items/atmp/_home/_main/index.html | H3: N/D | I3: 5 | J3: Consultar política atual | K3: Não confirmado | L3: Não informado | M3: APC deve ser conferido antes da submissão. Tempo editorial não informado de forma verificável. | N3: https://intlpress.com/site/pub/pages/journals/items/atmp/_home/_main/index.html
A4: Brazilian Journal of Physics | B4: BJP | C4: Springer Nature | D4: 1.7 | E4: física | F4: Pesquisa experimental, teórica e computacional em física, incluindo física atômica, matéria condensada, nuclear, óptica, partículas, física estatística, sistemas complexos e áreas correlatas. | G4: https://www.springer.com/journal/13538 | H4: N/D | I4: 4 | J4: Consultar política atual | K4: Híbrido/consultar | L4: Não informado | M4: APC deve ser conferido antes da submissão. Tempo editorial não informado de forma verificável. | N4: https://www.springer.com/journal/13538
A5: Canadian Journal of Physics | B5: Can. J. Phys. | C5: Canadian Science Publishing | D5: 1.1 | E5: física | F5: Pesquisa ampla em física, incluindo física atômica e molecular, matéria condensada, partículas, nuclear, fluidos e plasmas, óptica, física matemática, relatividade, cosmologia e gravitação. | G5: https://cdnsciencepub.com/journal/cjp | H5: N/D | I5: 4 | J5: Consultar política atual | K5: Não confirmado | L5: Não informado | M5: APC deve ser conferido antes da submissão. Tempo editorial não informado de forma verificável. | N5: https://cdnsciencepub.com/journal/cjp
A6: Chinese Journal of Physics | B6: Chin. J. Phys. | C6: Elsevier | D6: 4.6 | E6: física | F6: The Chinese Journal of Physics publishes important advances in various branches in physics, including: Gravitation and Astrophysics, General Physics. Statistical and Quantum Mechanics, etc. Quantum Information and Quantum Computation | G6: https://www.journals.elsevier.com/chinese-journal-of-physics | H6: N/D | I6: 5 | J6: Consultar política atual | K6: Híbrido/consultar | L6: Não informado | M6: APC deve ser conferido antes da submissão. Tempo editorial não informado de forma verificável. | N6: https://www.journals.elsevier.com/chinese-journal-of-physics
A7: Classical and Quantum Gravity | B7: CQG | C7: IOP Publishing | D7: 3.7 | E7: física | F7: Classical and Quantum Gravity is an established journal for physicists, mathematicians and cosmologists in the fields of gravitation and the theory of spacetime. The journal is now the acknowledged world leader in classical relativity and all areas of quantum gravity. | G7: https://iopscience.iop.org/journal/0264-9381 | H7: https://iopscience.iop.org/article/10.1088/0264-9381/11/5/001 | I7: 5 | J7: Consultar política atual | K7: Híbrido/consultar | L7: Não informado | M7: APC deve ser conferido antes da submissão. Tempo editorial não informado de forma verificável. | N7: https://iopscience.iop.org/journal/0264-9381
A8: Communications in Mathematical Physics | B8: CMP | C8: Springer Nature | D8: 2.9 | E8: física | F8: Pesquisa em física matemática com forte conteúdo matemático e motivação em problemas fundamentais da física moderna. | G8: https://www.springer.com/journal/220 | H8: N/D | I8: 5 | J8: OA: US$ 3.190 / £2.190 / €2.590 | K8: Híbrido | L8: 18 dias (mediana até 1ª decisão) | M8: Dados editoriais sujeitos a atualização; confirmar no site do periódico antes da submissão. | N8: https://www.springer.com/journal/220
A9: Gravitation and Cosmology | B9: Grav. Cosmol. | C9: Springer Nature | D9: 1 | E9: física | F9: Gravitação, cosmologia relativística, astrofísica relativística, soluções exatas, métodos matemáticos e fundamentos de teorias gravitacionais. | G9: https://www.springer.com/journal/10714 | H9: N/D | I9: 5 | J9: Consultar política atual | K9: Híbrido | L9: Não informado | M9: APC deve ser conferido antes da submissão. Tempo editorial não informado de forma verificável. | N9: https://www.springer.com/journal/10714
A10: International Journal of Modern Physics A | B10: IJMPA | C10: World Scientific | D10: 1.2 | E10: física | F10: Física de partículas, teoria quântica de campos, gravitação, cosmologia, física nuclear e temas relacionados de física moderna. | G10: https://www.worldscientific.com/worldscinet/ijmpa | H10: N/D | I10: 5 | J10: Consultar política atual | K10: Híbrido/consultar | L10: Não informado | M10: APC deve ser conferido antes da submissão. Tempo editorial não informado de forma verificável. | N10: https://www.worldscientific.com/worldscinet/ijmpa
A11: International Journal of Theoretical Physics | B11: IJTP | C11: Springer Nature | D11: 1.7 | E11: física | F11: Pesquisa em física teórica, fundamentos quânticos, gravitação, cosmologia, teoria de campos, física matemática e áreas correlatas. | G11: https://www.springer.com/journal/10773 | H11: N/D | I11: 5 | J11: Consultar política atual | K11: Híbrido/consultar | L11: Não informado | M11: APC deve ser conferido antes da submissão. Tempo editorial não informado de forma verificável. | N11: https://www.springer.com/journal/10773
A12: Journal of Computational Physics | B12: JCP | C12: Science Direct | D12: 3.8 | E12: física | F12: The Journal of Computational Physics (JCP) focuses on the computational aspects of physical problems. JCP encourages original scientific contributions in advanced mathematical and numerical modeling reflecting a combination of concepts, methods and principles which are often interdisciplinary in nature and span several areas of physics, mechanics, applied mathematics, statistics, applied geometry, computer science, chemistry and other scientific disciplines as well: the Journal's editors seek to emphasize methods that cross disciplinary boundaries. | G12: https://www.sciencedirect.com/journal/journal-of-computational-physics | H12: N/D | I12: 4 | J12: Consultar política atual | K12: Não confirmado | L12: Não informado | M12: APC deve ser conferido antes da submissão. Tempo editorial não informado de forma verificável. | N12: https://www.sciencedirect.com/journal/journal-of-computational-physics
A13: Journal of High Energy Physics | B13: JHEP | C13: Springer Nature | D13: 5.5 | E13: física | F13: The aim of the Journal of High Energy Physics (JHEP) is to ensure fast and efficient online publication tools to the scientific community, while keeping that community in charge of every aspect of the peer-review and publication process in order to ensure the highest quality standards in the journal. | G13: https://link.springer.com/journal/13130 | H13: N/D | I13: 5 | J13: Consultar política atual | K13: Open Access / SCOAP3 | L13: Não informado | M13: APC deve ser conferido antes da submissão. Tempo editorial não informado de forma verificável. | N13: https://link.springer.com/journal/13130
... A28: Theoretical and Mathematical Physics | B28: TMP | C28: Springer Nature | D28: 1.1 | E28: física | F28: Pesquisa em física teórica e matemática, incluindo teoria quântica de campos, sistemas integráveis, gravitação, cosmologia e métodos matemáticos. | G28: https://www.springer.com/journal/11232 | H28: N/D | I28: 5 | J28: Consultar política atual | K28: Híbrido/consultar | L28: Não informado | M28: APC deve ser conferido antes da submissão. Tempo editorial não informado de forma verificável. | N28: https://www.springer.com/journal/11232
A29: Action in Teacher Education | B29: ATE | C29: Association of Teacher Educators(ATE) | D29: N/D | E29: matemática | F29: Designed for a general teacher ed audience, but it does publish mathematics-specific articles. Particularly interested in action research articles. | G29: https://ate1.org/ate-publications | H29: N/D | I29: 3 | J29: Consultar política atual | K29: Membros/assinatura | L29: 3–4 meses | M29: APC deve ser conferido antes da submissão. | N29: https://docs.google.com/spreadsheets/d/1wSi_RMs07HmPMkirnmFInYvAovt0vWFP9lLaMk694Cc/htmlview/sheet?gid=0&headers=true
A30: AERA Open | B30: AERA Open | C30: American Educational Research Association (AERA) | D30: 2.8 | E30: matemática | F30: "AERA Open is a peer-reviewed, open access journal published by the American Educational Research Association (AERA). With an emphasis on rapid review and dissemination, AERA Open aims to advance knowledge through theoretical and empirical study across arenas of inquiry related to education and learning. AERA Open emphasizes publishing scientific and scholarly work that adds to knowledge incrementally and cumulatively. AERA Open also serves as a venue for innovation, novel inquiry and ideas, interdisciplinary bridge building, and research that fosters the connection of research to practice and practice to research." | G30: https://www.google.com/search?q=%22AERA+Open%22+official+journal | H30: N/D | I30: 3 | J30: Consultar política atual | K30: Open Access | L30: 4–6 meses | M30: Homepage oficial não foi confirmada; a URL fornecida é uma busca de localização. APC deve ser conferido antes da submissão. | N30: https://docs.google.com/spreadsheets/d/1wSi_RMs07HmPMkirnmFInYvAovt0vWFP9lLaMk694Cc/htmlview/sheet?gid=0&headers=true
A31: African Journal of Research in Science, Mathematics and Technology Education | B31: AJRSMTE | C31: Taylor & Francis | D31: 0.5 | E31: matemática | F31: "African Journal of Research in Mathematics, Science and Technology Education (AJRMSTE) is to disseminate, as widely as possible, high quality research findings and well written articles on Curriculum Studies; Teacher Education; Education for Development; Mathematics Education; Science Education; Design & Technology Education and Computer Education. Articles that promote the understanding of curricular policy and diverse socio-cultural issues and those which stimulate epistemological and methodological debates are welcome. The editorial board welcomes articles that will contribute to the overall development of science, mathematics, technology and environmental education in Africa. The focus being the development of research capacity in Africa, AJRMSTE assists first time authors in achieving the high standards to which the journal is committed. Naturally, the journal welcomes contributions from more experienced authors as well." | G31: https://www.google.com/search?q=%22African+Journal+of+Research+in+Science%2C+Mathematics+and+Technology+Education%22+official+journal | H31: N/D | I31: 4 | J31: Consultar política atual | K31: Híbrido | L31: 3–4 meses | M31: Homepage oficial não foi confirmada; a URL fornecida é uma busca de localização. APC deve ser conferido antes da submissão. | N31: https://docs.google.com/spreadsheets/d/1wSi_RMs07HmPMkirnmFInYvAovt0vWFP9lLaMk694Cc/htmlview/sheet?gid=0&headers=true
A32: American Educational Research Journal | B32: AERJ | C32: AERA | D32: 3.6 | E32: matemática | F32: "The American Educational Research Journal (AERJ, quarterly; approximately 960 pp./volume year) publishes original empirical and theoretical studies and analyses in education. The editors seek to publish articles from a wide variety of academic disciplines and substantive fields; they are looking for clear and significant contributions to the understanding and/or improvement of educational processes and outcomes. Manuscripts not appropriate for submission to this journal include essays, reviews, course evaluations, and brief reports of studies to address a narrow question." | G32: https://www.google.com/search?q=%22American+Educational+Research+Journal%22+official+journal | H32: N/D | I32: 3 | J32: Consultar política atual | K32: Assinatura | L32: Não informado | M32: Homepage oficial não foi confirmada; a URL fornecida é uma busca de localização. APC deve ser conferido antes da submissão. Tempo editorial não informado de forma verificável. | N32: https://docs.google.com/spreadsheets/d/1wSi_RMs07HmPMkirnmFInYvAovt0vWFP9lLaMk694Cc/htmlview/sheet?gid=0&headers=true
A33: Asian Journal for Mathematics Education | B33: AJME | C33: Sage | D33: N/D | E33: matemática | F33: "Asian Journal for Mathematics Education is a peer-reviewed open access journal. The mission of the journal is to contribute to the advancement of mathematics education research, theory and practice in Asia and, more generally, the world. The journal seeks to publish high-quality original research and scholarly articles focusing on various areas/topics in mathematics education. | G33: https://www.google.com/search?q=%22Asian+Journal+for+Mathematics+Education%22+official+journal | H33: N/D | I33: 4 | J33: Consultar política atual | K33: Open Access | L33: Não informado | M33: Homepage oficial não foi confirmada; a URL fornecida é uma busca de localização. APC deve ser conferido antes da submissão. Tempo editorial não informado de forma verificável. | N33: https://docs.google.com/spreadsheets/d/1wSi_RMs07HmPMkirnmFInYvAovt0vWFP9lLaMk694Cc/htmlview/sheet?gid=0&headers=true
A34: Australian Mathematics Education Journal | B34: AMEJ | C34: Australian Association of Mathematics Teachers(AAMT) | D34: N/D | E34: matemática | F34: "There are two defined sections: Section 1 is suitable for an audience of upper-primary and middle-school teachers and Section 2 is directed toward mathematics educators of senior high school and tertiary levels." | G34: https://www.google.com/search?q=%22Australian+Mathematics+Education+Journal%22+official+journal | H34: N/D | I34: 4 | J34: Consultar política atual | K34: Membros | L34: Não informado | M34: Segundo a fonte de referência, não estava aceitando submissões no início de 2026; confirmar situação atual. Homepage oficial não foi confirmada; a URL fornecida é uma busca de localização. APC deve ser conferido antes da submissão. Tempo editorial não informado de forma verificável. | N34: https://docs.google.com/spreadsheets/d/1wSi_RMs07HmPMkirnmFInYvAovt0vWFP9lLaMk694Cc/htmlview/sheet?gid=0&headers=true
A35: Australian Mathematics Teacher | B35: See AMEJ | C35: Australian Association of Mathematics Teachers(AAMT) | D35: N/D | E35: matemática | F35: Now AMEJ (but AMEJ possibly defunct) | G35: https://www.google.com/search?q=%22Australian+Mathematics+Teacher%22+official+journal | H35: N/D | I35: 4 | J35: Consultar política atual | K35: Descontinuado | L35: Não informado | M35: Publicação descontinuada; sucedida/absorvida por estruturas editoriais posteriores da AAMT. Homepage oficial não foi confirmada; a URL fornecida é uma busca de localização. APC deve ser conferido antes da submissão. Tempo editorial não informado de forma verificável. | N35: https://docs.google.com/spreadsheets/d/1wSi_RMs07HmPMkirnmFInYvAovt0vWFP9lLaMk694Cc/htmlview/sheet?gid=0&headers=true
A36: Australian Primary Mathematics Classroom | B36: APMC | C36: Australian Association of Mathematics Teachers(AAMT) | D36: N/D | E36: matemática | F36: "APMC publishes papers considering the teaching and learning of mathematics applicable to early years (pre-F) and primary school students (Years F–6/7). Papers tend to have a very practical focus with reports and ideas for teaching activities, as well as reporting research which has a direct impact on classroom teaching. Papers will assist educators who may not have specific mathematics training to understand how children learn concepts which are built on in later years of schooling." | G36: https://www.google.com/search?q=%22Australian+Primary+Mathematics+Classroom%22+official+journal | H36: N/D | I36: 3 | J36: Consultar política atual | K36: Membros | L36: Não informado | M36: Homepage oficial não foi confirmada; a URL fornecida é uma busca de localização. APC deve ser conferido antes da submissão. Tempo editorial não informado de forma verificável. | N36: https://docs.google.com/spreadsheets/d/1wSi_RMs07HmPMkirnmFInYvAovt0vWFP9lLaMk694Cc/htmlview/sheet?gid=0&headers=true
A37: Australian Senior Mathematics Journal | B37: See AMEJ | C37: Australian Association of Mathematics Teachers(AAMT) | D37: N/D | E37: matemática | F37: Now AMEJ (but AMEJ possibly defunct) | G37: https://www.google.com/search?q=%22Australian+Senior+Mathematics+Journal%22+official+journal | H37: N/D | I37: 3 | J37: Consultar política atual | K37: Descontinuado | L37: Não informado | M37: Publicação descontinuada; confirmar alternativas atuais da AAMT. Homepage oficial não foi confirmada; a URL fornecida é uma busca de localização. APC deve ser conferido antes da submissão. Tempo editorial não informado de forma verificável. | N37: https://docs.google.com/spreadsheets/d/1wSi_RMs07HmPMkirnmFInYvAovt0vWFP9lLaMk694Cc/htmlview/sheet?gid=0&headers=true
A38: British Journal for the History of Mathematics | B38: BJHM | C38: Taylor and Francis | D38: 0.4 (2022) | E38: matemática | F38: História da matemática em amplo espectro cronológico e geográfico, incluindo contextos culturais, filosóficos e institucionais. | G38: https://www.tandfonline.com/journals/tbsh21 | H38: N/D | I38: 3 | J38: Consultar política atual | K38: Open Access | L38: ≈6 meses | M38: APC deve ser conferido antes da submissão. | N38: https://docs.google.com/spreadsheets/d/1wSi_RMs07HmPMkirnmFInYvAovt0vWFP9lLaMk694Cc/htmlview/sheet?gid=0&headers=true
A39: Canadian Journal of Science, Mathematics and Technology Education | B39: CJSMTE | C39: Springer | D39: N/D | E39: matemática | F39: "The Canadian Journal of Science, Mathematics and Technology Education is the premier Canadian academic journal, and one of the leading journals internationally, in the field of STEM education. Published in both English and French, the journal aims to be both Canadian and international in scope. The journal provides a forum for the publication of original articles in a variety of styles, including research investigations using experimental, qualitative, ethnographic, historical, philosophical, or case study approaches; critical reviews of the literature; policy perspectives; and position papers, curriculum arguments, and discussion of issues in teacher education." | G39: https://www.google.com/search?q=%22Canadian+Journal+of+Science%2C+Mathematics+and+Technology+Education%22+official+journal | H39: N/D | I39: 3 | J39: Consultar política atual | K39: Híbrido | L39: Não informado | M39: Homepage oficial não foi confirmada; a URL fornecida é uma busca de localização. APC deve ser conferido antes da submissão. Tempo editorial não informado de forma verificável. | N39: https://docs.google.com/spreadsheets/d/1wSi_RMs07HmPMkirnmFInYvAovt0vWFP9lLaMk694Cc/htmlview/sheet?gid=0&headers=true
A40: CHAPTERS in Education | B40: CHAPTERS | C40: Springer | D40: N/D | E40: matemática | F40: "CHAPTERS in Education is a new, innovative series designed to provide a dedicated outlet for single-chapter submissions across the broad field of education research. Unlike traditional journal articles that focus on primary research and specific research questions, the scope of CHAPTERS in Education is on secondary and reflective scholarship. Our state-of-the-art self-service portal ensures a streamlined process for submission, peer review, decision-making, and publication. Each accepted chapter is published Online First, assigned a DOI, and fully citable—providing authors with rapid visibility and impact. Chapters are later compiled into volumes on a first-in, first-out basis." | G40: https://www.google.com/search?q=%22CHAPTERS+in+Education%22+official+journal | H40: N/D | I40: 3 | J40: Consultar política atual | K40: Híbrido/consultar | L40: Não informado | M40: Homepage oficial não foi confirmada; a URL fornecida é uma busca de localização. APC deve ser conferido antes da submissão. Tempo editorial não informado de forma verificável. | N40: https://docs.google.com/spreadsheets/d/1wSi_RMs07HmPMkirnmFInYvAovt0vWFP9lLaMk694Cc/htmlview/sheet?gid=0&headers=true
... A104: Journal of Statistics and Data Science Education (formerly Journal of Statistics Education) | B104: JSDSE | C104: Taylor & Francis / American Statistical Association | D104: N/D | E104: matemática | F104: Ensino e aprendizagem de estatística e ciência de dados, currículo, pedagogia, tecnologia e formação de profissionais e docentes. | G104: https://www.tandfonline.com/journals/ujse21 | H104: N/D | I104: 3 | J104: Consultar política atual | K104: Open Access | L104: Não informado | M104: Periódico da American Statistical Association; antigo Journal of Statistics Education. APC deve ser conferido antes da submissão. Tempo editorial não informado de forma verificável. | N104: https://docs.google.com/spreadsheets/d/1wSi_RMs07HmPMkirnmFInYvAovt0vWFP9lLaMk694Cc/htmlview/sheet?gid=0&headers=true
A105: Journal of Teacher Education | B105: JTE | C105: sage | D105: 2.208 | E105: matemática | F105: Respected journal in teacher education; publishes all subject areas; ideal for TE studies that cut across disciplines. "The Journal of Teacher Education provides a vital forum for considering practice, policy, and research in teacher education. It examines some of the most timely and important topics in the field, such as: New Teacher Education Standards, Assessing the Outcomes of Teacher Education, Preparing Teachers to Meet the Needs of Diverse Populations, Teacher Education in a Global Society, The Research Base for Teacher Education, Accountability and Accreditation Issues, Collaborating with Arts and Sciences Faculties, Recruiting a More Diverse Teaching Force and Teacher Education Faculty, School-based and Partnership-based Teacher Education, Alternative Approaches to Teacher Education, High Stakes Testing for Teachers and Students, Leadership in 21st Century Schools of Education, The Changing Demographics of Schools and Schooling" Impact Factor: 2.208. Top Quartile in SJR Education Journal ranking. 17/219 in Education & Educational Research category (as of 2014). | G105: https://www.google.com/search?q=%22Journal+of+Teacher+Education%22+official+journal | H105: N/D | I105: 3 | J105: Consultar política atual | K105: Híbrido/consultar | L105: Não informado | M105: Homepage oficial não foi confirmada; a URL fornecida é uma busca de localização. APC deve ser conferido antes da submissão. Tempo editorial não informado de forma verificável. | N105: https://docs.google.com/spreadsheets/d/1wSi_RMs07HmPMkirnmFInYvAovt0vWFP9lLaMk694Cc/htmlview/sheet?gid=0&headers=true
A106: Journal of Technology and Teacher Education | B106: JTATE | C106: AACE | D106: N/D | E106: matemática | F106: "JTATE serves as a forum for the exchange of knowledge about the use of information technology in teacher education. Journal content covers preservice and inservice teacher education, graduate programs in areas such as curriculum and instruction, educational administration, staff development instructional technology, and educational computing." Acceptance Rate: rumor has it that there is no back-log here. | G106: https://www.google.com/search?q=%22Journal+of+Technology+and+Teacher+Education%22+official+journal | H106: N/D | I106: 3 | J106: Consultar política atual | K106: Híbrido | L106: Não informado | M106: Homepage oficial não foi confirmada; a URL fornecida é uma busca de localização. APC deve ser conferido antes da submissão. Tempo editorial não informado de forma verificável. | N106: https://docs.google.com/spreadsheets/d/1wSi_RMs07HmPMkirnmFInYvAovt0vWFP9lLaMk694Cc/htmlview/sheet?gid=0&headers=true
A107: Journal of the Learning Sciences | B107: JLS | C107: ISLS, Taylor & Francis | D107: 6.083 | E107: matemática | F107: Not specifically mathematics education, but it is worth mentioning because of its ranking (see below). "The Journal of the Learning Sciences provides a multidisciplinary forum for the presentation and discussion of research on education and learning. Emphasis is placed on important ideas that can change our understanding of learning as well as the practice of education. Articles evolve from disciplines such as artificial intelligence, cognitive science, cognitive and educational psychology, cognitive anthropology, education, and educational psychology." Impact factor: 1.767. Top Quartile in SJR Education Journal ranking. | G107: https://www.google.com/search?q=%22Journal+of+the+Learning+Sciences%22+official+journal | H107: N/D | I107: 4 | J107: Consultar política atual | K107: Híbrido/consultar | L107: ≈6 dias triagem; ≈122 dias após revisão | M107: Homepage oficial não foi confirmada; a URL fornecida é uma busca de localização. APC deve ser conferido antes da submissão. | N107: https://docs.google.com/spreadsheets/d/1wSi_RMs07HmPMkirnmFInYvAovt0vWFP9lLaMk694Cc/htmlview/sheet?gid=0&headers=true
A108: Journal of Urban Mathematics Education | B108: JUME | C108: Texas A&M University’s Aggie STEM | D108: N/D | E108: matemática | F108: "The mission of the journal is to foster a transformative global academic space in mathematics that embraces critical research, emancipatory pedagogy, and scholarship of engagement in urban communities. Here, the view of the urban domain extends beyond the geographical context, into the lives of people within the multitude of cultural, social, and political spaces in which mathematics teaching and learning takes place. The Editorial Team embraces the idea that theory and practice are inextricably linked, and can work together in a multiplicity of ways. We welcome submissions from emerging and noted scholars whose research in the urban domain offers important and innovative contributions to the theory and practice of mathematics teaching, learning, and policy." | G108: https://www.google.com/search?q=%22Journal+of+Urban+Mathematics+Education%22+official+journal | H108: N/D | I108: 4 | J108: Consultar política atual | K108: Open Access | L108: ≈2–4 meses | M108: Homepage oficial não foi confirmada; a URL fornecida é uma busca de localização. APC deve ser conferido antes da submissão. | N108: https://docs.google.com/spreadsheets/d/1wSi_RMs07HmPMkirnmFInYvAovt0vWFP9lLaMk694Cc/htmlview/sheet?gid=0&headers=true
A109: Journal on Mathematics Education | B109: IndoMS-JME | C109: Universitas Sriwijaya and the Indonesian Mathematical Society | D109: N/D | E109: matemática | F109: "The journal functions as a platform for the dissemination of innovative ideas and significant advancements in mathematics education. Its goal is to represent the wide array of research interests and the diverse methodologies employed to investigate these interests. Rather than concentrating exclusively on a specific mathematics teaching program, the journal addresses the methodological, didactical, political, and socio-cultural dimensions of mathematics teaching and learning. IndoMS-JME invites research from all approaches, with a particular emphasis on high-quality articles that possess global relevance and impact on mathematics learning." | G109: https://www.google.com/search?q=%22Journal+on+Mathematics+Education%22+official+journal | H109: N/D | I109: 4 | J109: Consultar política atual | K109: Open Access | L109: ≈1–2 meses | M109: Homepage oficial não foi confirmada; a URL fornecida é uma busca de localização. APC deve ser conferido antes da submissão. | N109: https://docs.google.com/spreadsheets/d/1wSi_RMs07HmPMkirnmFInYvAovt0vWFP9lLaMk694Cc/htmlview/sheet?gid=0&headers=true
A110: Kentucky Journal of Mathematics Teacher Education | B110: KJMTE | C110: AMTE - Kentucky affiliate | D110: N/D | E110: matemática | F110: Formação de professores de matemática, prática docente, desenvolvimento profissional e pesquisa aplicada à educação matemática. | G110: https://www.google.com/search?q=%22Kentucky+Journal+of+Mathematics+Teacher+Education%22+official+journal | H110: N/D | I110: 4 | J110: Consultar política atual | K110: Open Access | L110: Não informado | M110: Homepage oficial não foi confirmada; a URL fornecida é uma busca de localização. APC deve ser conferido antes da submissão. Tempo editorial não informado de forma verificável. | N110: https://docs.google.com/spreadsheets/d/1wSi_RMs07HmPMkirnmFInYvAovt0vWFP9lLaMk694Cc/htmlview/sheet?gid=0&headers=true
A111: Learning and Teaching Mathematics | B111: LTM | C111: AMESA | D111: N/D | E111: matemática | F111: Learning and Teaching Mathematics provides a medium for stimulating and challenging ideas relating to mathematics teaching and learning at all levels. While this journal "listens" to research, it does not publish conventional research reports; rather it presents articles that describe or discuss mathematics teaching and learning from the perspective of the practitioner. Learning and Teaching Mathematics is a peer-reviewed journal, published two times a year and distributed to all members of AMESA (Association for Mathematics Education of South Africa - AMESA - is the professional association for Mathematics Education in South Africa.) | G111: https://www.google.com/search?q=%22Learning+and+Teaching+Mathematics%22+official+journal | H111: N/D | I111: 4 | J111: Consultar política atual | K111: Não confirmado | L111: Não informado | M111: Homepage oficial não foi confirmada; a URL fornecida é uma busca de localização. APC deve ser conferido antes da submissão. Tempo editorial não informado de forma verificável. | N111: https://docs.google.com/spreadsheets/d/1wSi_RMs07HmPMkirnmFInYvAovt0vWFP9lLaMk694Cc/htmlview/sheet?gid=0&headers=true
A112: Math Horizons | B112: MH | C112: MAA | D112: N/D | E112: matemática | F112: A journal that publishes reader-friendly articles that connect mathematics to other aspects of life (e.g., art, television, politics). Geared toward undergrads. | G112: https://www.google.com/search?q=%22Math+Horizons%22+official+journal | H112: N/D | I112: 5 | J112: Consultar política atual | K112: Não confirmado | L112: Não informado | M112: Homepage oficial não foi confirmada; a URL fornecida é uma busca de localização. APC deve ser conferido antes da submissão. Tempo editorial não informado de forma verificável. | N112: https://docs.google.com/spreadsheets/d/1wSi_RMs07HmPMkirnmFInYvAovt0vWFP9lLaMk694Cc/htmlview/sheet?gid=0&headers=true
A113: MathAMATYC Educator | B113: MathAMATYC | C113: American Mathematical Association of Two-Year Colleges (AMATYC) | D113: N/D | E113: matemática | F113: "Its purpose is to provide an avenue of communication for all mathematics educators concerned with the views, ideas, and experiences pertinent to two-year college teachers and students.Subject Matter: The editorial team of MathAMATYC Educator is interested in articles that focus on mathematics teaching and learning at two-year colleges." Accept both research-based and practically-focused articles 3 issues per year Focused on issues relevant to math education at two-year colleges, community colleges, post-secondary level, remediation, etc. | G113: https://www.google.com/search?q=%22MathAMATYC+Educator%22+official+journal | H113: N/D | I113: 4 | J113: Consultar política atual | K113: Não confirmado | L113: Não informado | M113: Homepage oficial não foi confirmada; a URL fornecida é uma busca de localização. APC deve ser conferido antes da submissão. Tempo editorial não informado de forma verificável. | N113: https://docs.google.com/spreadsheets/d/1wSi_RMs07HmPMkirnmFInYvAovt0vWFP9lLaMk694Cc/htmlview/sheet?gid=0&headers=true
A114: Mathematical Thinking and Learning | B114: MTL | C114: Taylor and Francis | D114: 1.6 (2022) | E114: matemática | F114: An international journal interested in interdisciplinary or multiple perspectives on mathematical (you guessed it) thinking and learning, with a particular emphasis on development of reasoning, innovative instructional practices, and cross-cultural comparisons. "The international mathematics education community is maturing at a rapid and exciting rate. Although this community has developed its own research perspectives and theoretical frameworks, it continues to expand its horizons by drawing upon new theories and research in mathematics, psychology, sociology, philosophy, anthropology, and information technology. Mathematical Thinking and Learning is directed at researchers interested in mathematics education from any of these perspectives, with a particular focus on mathematical thinking, reasoning, and learning. ... In addition to receiving research articles, the journal invites articles that present theoretical and philosophical analyses of issues related to the previous topics." Was publicly described by Dick Lesh at PME-NA 32 as the best journal in mathematics education. Is often considered one of the Top 3 research journals in mathematics education, behind the Journal for Research in Mathematics Education and with Educational Studies in Mathematics. Acceptance rate is below 20%. Top Quartile in SJR Education Journal ranking. Graded "A" by Toerner and Arzarello (2012). | G114: https://www.google.com/search?q=%22Mathematical+Thinking+and+Learning%22+official+journal | H114: N/D | I114: 4 | J114: Consultar política atual | K114: Híbrido/consultar | L114: ≈3 meses | M114: Homepage oficial não foi confirmada; a URL fornecida é uma busca de localização. APC deve ser conferido antes da submissão. | N114: https://docs.google.com/spreadsheets/d/1wSi_RMs07HmPMkirnmFInYvAovt0vWFP9lLaMk694Cc/htmlview/sheet?gid=0&headers=true
A115: Mathematics Education (MathEdu) | B115: ME | C115: Elsevier | D115: N/D | E115: matemática | F115: Formerly known as International Electronic Journal of Mathematics Education (IEJME, ISSN: 1306-3030), changed to Mathematics Education (MathEdu) on March 25, 2015. The former named International Electronic Journal of Mathematics Education (IEJME) is an online academic journal devoted to reflect a variety of research ideas and methods in the field of mathematics education. MathEdu aims to stimulate discussions at all levels of mathematics education through significant and innovative research studies. The Journal welcomes articles highlighting empirical as well as theoretical research studies, which have a perspective wider than local or national interest. Volumes 1 through 8 are listed as IEJME, volume 9 began using the new title but retained the volume number. MathEdu is published three times a year, in January, May and September double-blind, peer reviewed with a 5% acceptance rate Abstracted/Indexed in: EBSCO, Elsevier, Cabell’s Directory Index, Index Copernicus, DOAJ, MathDi, EdNA Online Database, NewJour ISSN: 1306-3030 | G115: https://www.google.com/search?q=%22Mathematics+Education+%28MathEdu%29%22+official+journal | H115: N/D | I115: 4 | J115: Consultar política atual | K115: Híbrido/consultar | L115: Não informado | M115: Homepage oficial não foi confirmada; a URL fornecida é uma busca de localização. APC deve ser conferido antes da submissão. Tempo editorial não informado de forma verificável. | N115: https://docs.google.com/spreadsheets/d/1wSi_RMs07HmPMkirnmFInYvAovt0vWFP9lLaMk694Cc/htmlview/sheet?gid=0&headers=true
A116: Mathematics Education Research Journal | B116: MERJ | C116: MERGA | D116: N/D | E116: matemática | F116: Accepts various kinds of articles that are either of interest to an international audience or specifically the Australasian audience. "MERJ, an official journal of the Mathematics Education Research Group of Australasia, Inc. (MERGA), is an international refereed journal that provides a forum for the publication of research on the teaching and learning of mathematics at all levels. Submissions of high quality papers should normally be of general interest to an international readership, but papers exploring specifically Australasian issues, are welcome." | G116: https://www.google.com/search?q=%22Mathematics+Education+Research+Journal%22+official+journal | H116: N/D | I116: 4 | J116: Consultar política atual | K116: Híbrido | L116: Não informado | M116: Homepage oficial não foi confirmada; a URL fornecida é uma busca de localização. APC deve ser conferido antes da submissão. Tempo editorial não informado de forma verificável. | N116: https://docs.google.com/spreadsheets/d/1wSi_RMs07HmPMkirnmFInYvAovt0vWFP9lLaMk694Cc/htmlview/sheet?gid=0&headers=true
A117: Mathematics Education Review | B117: MER | C117: Association of Mathematics Education Teachers (UK) | D117: N/D | E117: matemática | F117: MER focuses on articles that are meant for teacher educators (e.g., a special issue about lesson observations of student teachers). | G117: https://www.google.com/search?q=%22Mathematics+Education+Review%22+official+journal | H117: N/D | I117: 4 | J117: Consultar política atual | K117: Não confirmado | L117: Não informado | M117: Homepage oficial não foi confirmada; a URL fornecida é uma busca de localização. APC deve ser conferido antes da submissão. Tempo editorial não informado de forma verificável. | N117: https://docs.google.com/spreadsheets/d/1wSi_RMs07HmPMkirnmFInYvAovt0vWFP9lLaMk694Cc/htmlview/sheet?gid=0&headers=true
A118: Mathematics in School | B118: MS | C118: The Mathematical Association (Britain) | D118: N/D | E118: matemática | F118: "Mathematics in School is a lively journal providing contributions from mathematics practitioners at all levels. It reflects the best of current thinking and practice, exploring possible development and sharing practical experience. As well as articles covering mathematics teaching at both primary and secondary levels, each issue provides practical advice on general teaching methods, information on the analysis of official reports and reviews of classroom based projects and surveys. It is aimed at teachers of primary and secondary pupils, students in training and all those with a professional interest in mathematics education." | G118: https://www.google.com/search?q=%22Mathematics+in+School%22+official+journal | H118: N/D | I118: 4 | J118: Consultar política atual | K118: Não confirmado | L118: Não informado | M118: Homepage oficial não foi confirmada; a URL fornecida é uma busca de localização. APC deve ser conferido antes da submissão. Tempo editorial não informado de forma verificável. | N118: https://docs.google.com/spreadsheets/d/1wSi_RMs07HmPMkirnmFInYvAovt0vWFP9lLaMk694Cc/htmlview/sheet?gid=0&headers=true
A119: Mathematics Teacher (Discontinued publication in 2019) | B119: MT | C119: National Council of Teachers of Mathematics (NCTM) | D119: N/D | E119: matemática | F119: SPUN OUT OF MATHEMATICS TEACHER AND OTHER NCTM TEACHER JOURNALS IN 2019. | G119: https://www.google.com/search?q=%22Mathematics+Teacher%0A%28Discontinued+publication+in+2019%29%22+official+journal | H119: N/D | I119: 4 | J119: Consultar política atual | K119: Descontinuado | L119: Não informado | M119: Publicação descontinuada em 2019; conteúdo editorial foi reorganizado pelo NCTM. Homepage oficial não foi confirmada; a URL fornecida é uma busca de localização. APC deve ser conferido antes da submissão. Tempo editorial não informado de forma verificável. | N119: https://docs.google.com/spreadsheets/d/1wSi_RMs07HmPMkirnmFInYvAovt0vWFP9lLaMk694Cc/htmlview/sheet?gid=0&headers=true
... A140: Research Journal of Mathematics and Technology | B140: RJMT | C140: Research Journal of Mathematics and Technology | D140: N/D | E140: matemática | F140: The aims and scope, areas of Interests, submission guidelines are identical to those at eJMT (see above entry for eJMT) The Research Journal of Mathematics and Technology is a printed version of selected articles from the Electronic Journal of Mathematics and Technology (eJMT: https://php.radford.edu/~ejmt/), Published semi-annually in June and December of each year. First issue in June of 2012. | G140: https://www.google.com/search?q=%22Research+Journal+of+Mathematics+and+Technology%22+official+journal | H140: N/D | I140: 3 | J140: Consultar política atual | K140: Não confirmado | L140: Não informado | M140: Homepage oficial não foi confirmada; a URL fornecida é uma busca de localização. APC deve ser conferido antes da submissão. Tempo editorial não informado de forma verificável. | N140: https://docs.google.com/spreadsheets/d/1wSi_RMs07HmPMkirnmFInYvAovt0vWFP9lLaMk694Cc/htmlview/sheet?gid=0&headers=true
A141: Review of Educational Research | B141: RER | C141: AERA | D141: 13.551 | E141: matemática | F141: "The Review of Educational Research (RER, quarterly, begun in 1931; approximately 640 pp./volume year) publishes critical, integrative reviews of research literature bearing on education. Such reviews should include conceptualizations, interpretations, and syntheses of literature and scholarly work in a field broadly relevant to education and educational research. RER encourages the submission of research relevant to education from any discipline, such as reviews of research in psychology, sociology, history, philosophy, political science, economics, computer science, statistics, anthropology, and biology, provided that the review bears on educational issues. RER does not publish original empirical research unless it is incorporated in a broader integrative review. RER will occasionally publish solicited, but carefully refereed, analytic reviews of special topics, particularly from disciplines infrequently represented." | G141: https://www.google.com/search?q=%22Review+of+Educational+Research%22+official+journal | H141: N/D | I141: 3 | J141: Consultar política atual | K141: Híbrido | L141: Não informado | M141: Homepage oficial não foi confirmada; a URL fornecida é uma busca de localização. APC deve ser conferido antes da submissão. Tempo editorial não informado de forma verificável. | N141: https://docs.google.com/spreadsheets/d/1wSi_RMs07HmPMkirnmFInYvAovt0vWFP9lLaMk694Cc/htmlview/sheet?gid=0&headers=true
A142: Review of Research in Education | B142: RRE | C142: AERA | D142: 7.3 | E142: matemática | F142: "Review of Research in Education (RRE), published annually since 1973 (approximately 416 pp./volume year), provides an overview and descriptive analysis of selected topics of relevant research literature through critical and synthesizing essays. Articles are usually solicited for specific RRE issues. There may also be calls for papers. RRE promotes discussion and controversy about research problems in addition to pulling together and summarizing the work in a field." | G142: https://www.google.com/search?q=%22Review+of+Research+in+Education%22+official+journal | H142: N/D | I142: 3 | J142: Consultar política atual | K142: Híbrido | L142: Não informado | M142: Homepage oficial não foi confirmada; a URL fornecida é uma busca de localização. APC deve ser conferido antes da submissão. Tempo editorial não informado de forma verificável. | N142: https://docs.google.com/spreadsheets/d/1wSi_RMs07HmPMkirnmFInYvAovt0vWFP9lLaMk694Cc/htmlview/sheet?gid=0&headers=true
A143: Revista de Investigatción en Didáctica de la Matemática | B143: REDIMAT | C143: Hypatia Press | D143: N/D | E143: matemática | F143: 'REDIMAT. Revista de Investigación en Didactica de las Mathematics is an electronic journal that publishes articles in the field of mathematics education that represent a significant contribution to understanding and improving teaching and learning in mathematics. REDIMAT publishes original empirical and theoretical works, based on scientific investigations, with different theoretical and methodological approaches." | G143: https://www.google.com/search?q=%22Revista+de+Investigatci%C3%B3n+en+Did%C3%A1ctica+de+la+Matem%C3%A1tica%22+official+journal | H143: N/D | I143: 4 | J143: Consultar política atual | K143: Não confirmado | L143: Não informado | M143: Homepage oficial não foi confirmada; a URL fornecida é uma busca de localização. APC deve ser conferido antes da submissão. Tempo editorial não informado de forma verificável. | N143: https://docs.google.com/spreadsheets/d/1wSi_RMs07HmPMkirnmFInYvAovt0vWFP9lLaMk694Cc/htmlview/sheet?gid=0&headers=true
A144: Revista do Professor de Matemática | B144: RPM | C144: Sociedade Brasileira de Matemática (SBM) | D144: N/D | E144: matemática | F144: A revista acolhe matéria, a mais variada, de nível elementar ou avançado, dentro dos parâmetros do ensino básico. O principal critério de seleção do que deve ser publicado é o bom gosto e correção da matéria submetida. Uma experiência interessante em sala de aula, um problema que suscita uma questão pouco conhecida, uma história que valha a pena ser contada, tudo isso pode ser tema de artigos de interesse dos leitores. Em contraste, não se aceitam simples transcrições do que se encontra em livros nem resumo de aulas de rotina. Toda matéria submetida para publicação deve ser de leitura agradável, escrita com uma distribuição adequada de parágrafos e seções e contendo, inclusive, uma introdução, onde se diga claramente o objetivo do que se vai apresentar. É no início do trabalho que o autor tem sua oportunidade de cativar o interesse do leitor. É importante que o autor tenha em conta o público a que se dirige, lembrando que o trabalho é escrito para ser lido e apreciado; provavelmente o leitor terá dificuldade em ler um artigo escrito sem muita clareza, mesmo que em linguagem rigorosa e exata. Se possível o autor deve examinar seu trabalho do ponto de vista de quem lê e não somente do ponto de vista de quem escreve. A colaboração do leitor, submetendo artigos, contando suas experiências e apresentando suas idéias, é essencial para o enriquecimento da revista e será sempre bem acolhida pelo Comitê Editorial. | G144: https://rpm.org.br/BuscaAvancada.aspx | H144: N/D | I144: 5 | J144: Consultar política atual | K144: Não confirmado | L144: Não informado | M144: APC deve ser conferido antes da submissão. Tempo editorial não informado de forma verificável. | N144: https://docs.google.com/spreadsheets/d/1wSi_RMs07HmPMkirnmFInYvAovt0vWFP9lLaMk694Cc/htmlview/sheet?gid=0&headers=true
A145: Revista Matemática Universitária | B145: RMU | C145: Sociedade Brasileira de Matemática (SBM) | D145: N/D | E145: matemática | F145: Orientação aos autores Artigos submetidos à revista devem evitar tecnicalidades excessivas e os estilos de notas de sala de aula ou de livro texto. Observamos também que a RMU não é um veículo para artigos de pesquisa ou apresentações muito próximas de livros ou textos existentes. O artigo ideal deve capturar a atenção do leitor com uma introdução adequada e desenvolver o tema proposto de modo a tornar a leitura leve e prazerosa; deve-se manter em mente que a revista não se propõe a publicar textos para estudo, mas sim sugerir direções para isso. A RMU encoraja os membros da comunidade matemática brasileira e de outros países de língua portuguesa a submeterem para publicação artigos versando sobre temas de Matemática, voltada para alunos e professores de cursos de graduação, licenciatura e pós-graduação em Matemática ou em outras ciências exatas, nos seguintes formatos: exposições de tópicos não habituais nos programas de disciplinas de cursos de Matemática; ensaios de áreas de pesquisa atuais que deem uma boa ideia dos temas pesquisados e do estado atual da área; resenhas de livros, vídeos, filmes e outras produções técnicas ou artísticas relevantes; resenhas de sites; biografias de e entrevistas com matemáticos que tenham realizados contribuições significativas à Matemática; novas exposições de tópicos e resultados habituais, que contemplam, por exemplo, demonstrações não habituais e novas abordagens expositivas; textos de caráter histórico abordando ideias, eventos e personalidades relevantes; problemas (com soluções) para a Seção de Problemas; exemplos do uso de softwares matemáticos no ensino de graduação e pós-graduação, bem como na busca de evidência experimental para conjeturas; produções literárias diversas, que apresentem assuntos de interesse matemático. | G145: https://rmu.sbm.org.br/ | H145: https://rmu.sbm.org.br/wp-content/uploads/sites/27/2018/03/n31_Artigo01.pdf | I145: 5 | J145: Consultar política atual | K145: Não confirmado | L145: Não informado | M145: APC deve ser conferido antes da submissão. Tempo editorial não informado de forma verificável. | N145: https://docs.google.com/spreadsheets/d/1wSi_RMs07HmPMkirnmFInYvAovt0vWFP9lLaMk694Cc/htmlview/sheet?gid=0&headers=true
A146: Scatterplot | B146: Scatterplot | C146: Mathematical Association of America (MAA) | D146: N/D | E146: matemática | F146: "Scatterplot: The MAA Journal of Data Science serves the mathematics community by providing research and expository content at the intersection of mathematics, data science and educational practice. Suggested topics include pedagogy and teaching practice, development of curricula that combine mathematics and data science at the course or program level, intersections with other disciplines, social justice and ethics, and exposition of mathematical ideas used in data science applications. Teaching approaches that help grow and diversify the population of students in these fields are especially encouraged, as are contributions describing the experience of current students or recent graduates in applications and careers.” | G146: https://www.google.com/search?q=%22Scatterplot%22+official+journal | H146: N/D | I146: 5 | J146: Consultar política atual | K146: Não confirmado | L146: Não informado | M146: Homepage oficial não foi confirmada; a URL fornecida é uma busca de localização. APC deve ser conferido antes da submissão. Tempo editorial não informado de forma verificável. | N146: https://docs.google.com/spreadsheets/d/1wSi_RMs07HmPMkirnmFInYvAovt0vWFP9lLaMk694Cc/htmlview/sheet?gid=0&headers=true
A147: School Science and Mathematics | B147: SSM | C147: School Science and Mathematics Association | D147: 0.9 (2024) | E147: matemática | F147: "Founded in 1901, SSM is an international journal that is published monthly, October through May, emphasizing research on issues, concerns, and lessons within and between the disciplines of science and mathematics in the classroom. As a peer-refereed professional journal, it is a trusted resource for science and mathematics educators and is a leader in STEM integration articles." Types: Editorial, Problems, Research Articles, Review Articles, Innovations to Practice. "We publish research on issues, concerns, and lessons within and between the disciplines of science and mathematics in the classroom." | G147: https://www.google.com/search?q=%22School+Science+and+Mathematics%22+official+journal | H147: N/D | I147: 3 | J147: OA: ≈US$ 2.750 | K147: Híbrido | L147: ≈3 meses | M147: Homepage oficial não foi confirmada; a URL fornecida é uma busca de localização. | N147: https://docs.google.com/spreadsheets/d/1wSi_RMs07HmPMkirnmFInYvAovt0vWFP9lLaMk694Cc/htmlview/sheet?gid=0&headers=true
A148: Teachers and Teaching: Theory and Practice | B148: TT | C148: Taylor and Francis | D148: 3.143 | E148: matemática | F148: "Teachers and Teaching: theory and practice provides an international focal point for the publication of research on teachers and teaching, in particular on teacher thinking. It offers a means of communication and dissemination of completed research and research in progress, whilst also providing a forum for debate between researchers. This unique journal draws together qualitative and quantitative research from different countries and cultures which focus on the social, political and historical contexts of teaching as work. It includes theoretical reflections on the connections between theory and practice in teachers' work and other research of professional interest." | G148: https://www.google.com/search?q=%22Teachers+and+Teaching%3A+Theory+and+Practice%22+official+journal | H148: N/D | I148: 3 | J148: Consultar política atual | K148: Assinatura | L148: Não informado | M148: Homepage oficial não foi confirmada; a URL fornecida é uma busca de localização. APC deve ser conferido antes da submissão. Tempo editorial não informado de forma verificável. | N148: https://docs.google.com/spreadsheets/d/1wSi_RMs07HmPMkirnmFInYvAovt0vWFP9lLaMk694Cc/htmlview/sheet?gid=0&headers=true
A149: Teachers College Record | B149: TCR | C149: Teachers College, Columbia. | D149: N/D | E149: matemática | F149: "The Teachers College Record is a journal of research, analysis, and commentary in the field of education. It has been published continuously since 1900.'' | G149: https://www.google.com/search?q=%22Teachers+College+Record%22+official+journal | H149: N/D | I149: 3 | J149: Consultar política atual | K149: Open Access | L149: Não informado | M149: Homepage oficial não foi confirmada; a URL fornecida é uma busca de localização. APC deve ser conferido antes da submissão. Tempo editorial não informado de forma verificável. | N149: https://docs.google.com/spreadsheets/d/1wSi_RMs07HmPMkirnmFInYvAovt0vWFP9lLaMk694Cc/htmlview/sheet?gid=0&headers=true
A150: Teaching and Teacher Education | B150: TTE | C150: Elsevier | D150: 3.9 | E150: matemática | F150: "Teaching and Teacher Education aims to enhance theory, research, and practice in teaching and teacher education through the publication of papers concerned with the analysis of teaching, teaching effectiveness, the factors that determine teachers' thought processes and performances, and the social policies that affect teachers in all aspects and stages of their careers. The journal will recognize that many disciplines - psychology, sociology, anthropology, economics, political science, history, and philosophy - have important contributions to make to the achievement of its goals, and the Editors welcome contributions from them. In the absence of any dominant paradigm, the journal will allow varied approaches to offer empirical research, theoretical and conceptual analyses, and reviews (both qualitative and quantitative syntheses) of high quality. ... Papers should be concerned primarily with teachers, teaching, or teacher education at whatever grade, level, or whatever subject-matter, at any stage of the teacher's career." | G150: https://www.google.com/search?q=%22Teaching+and+Teacher+Education%22+official+journal | H150: N/D | I150: 3 | J150: OA: ≈US$ 2.350 | K150: Híbrido | L150: ≈6–7 meses | M150: Homepage oficial não foi confirmada; a URL fornecida é uma busca de localização. | N150: https://docs.google.com/spreadsheets/d/1wSi_RMs07HmPMkirnmFInYvAovt0vWFP9lLaMk694Cc/htmlview/sheet?gid=0&headers=true
A151: Teaching Children Mathematics (Discontinued publication in 2019) | B151: TCM | C151: NCTM | D151: N/D | E151: matemática | F151: "Teaching Children Mathematics (TCM) is intended as a resource for elementary school students, teachers, and teacher educators. The focus of the journal is on intuitive, exploratory investigations that use informal reasoning to help students develop a strong conceptual basis that leads to greater mathematical abstraction. The journal's articles have won numerous awards, including honors from the Society of National Association Publications." | G151: https://www.google.com/search?q=%22Teaching+Children+Mathematics%0A%28Discontinued+publication+in+2019%29%22+official+journal | H151: N/D | I151: 3 | J151: Consultar política atual | K151: Descontinuado | L151: Não informado | M151: Publicação descontinuada em 2019. Homepage oficial não foi confirmada; a URL fornecida é uma busca de localização. APC deve ser conferido antes da submissão. Tempo editorial não informado de forma verificável. | N151: https://docs.google.com/spreadsheets/d/1wSi_RMs07HmPMkirnmFInYvAovt0vWFP9lLaMk694Cc/htmlview/sheet?gid=0&headers=true
A152: Teaching for Excellence and Equity in Mathematics | B152: TEEM | C152: TODOS Mathematics for All. | D152: N/D | E152: matemática | F152: "The journal (TEEM) aims especially to engage mathematics education topics involving excellence and equity simultaneously (rather than either in isolation) in a way that connects research to classroom practice and can directly inform the practice of teachers or professional developers. To this end, articles are welcomed that relate to: (1) all students learning mathematics that is effective and appropriate for them, on and beyond grade level expectations, beyond computational abilities, as problem solvers, (2) a vision or example of what this looks like in the K-12 classroom (or courses for pre-service or in-service teachers), or (3) attention to the roles that language and culture (in a broad sense) have in teaching and learning. The journal defines equity broadly, including (but not limited to) issues of language, gender, ethnicity, and culture. TEEM welcomes addressing issues of language, culture, access, equity, and quality from diverse viewpoints: teachers, teacher-leaders, administrators, professional developers, teacher preparation faculty, etc. The peer-review process includes double-blind review by at least two external referees." | G152: https://www.google.com/search?q=%22Teaching+for+Excellence+and+Equity+in+Mathematics%22+official+journal | H152: N/D | I152: 4 | J152: Consultar política atual | K152: Não confirmado | L152: Não informado | M152: Homepage oficial não foi confirmada; a URL fornecida é uma busca de localização. APC deve ser conferido antes da submissão. Tempo editorial não informado de forma verificável. | N152: https://docs.google.com/spreadsheets/d/1wSi_RMs07HmPMkirnmFInYvAovt0vWFP9lLaMk694Cc/htmlview/sheet?gid=0&headers=true
A153: Teaching Mathematics and its Applications | B153: TMA | C153: Institute of Mathematics and its Applications (UK) | D153: 0.9 (2024) | E153: matemática | F153: "Teaching Mathematics and its Applications provides a forum for the exchange of ideas and experiences which contribute to the improvement of mathematics teaching and learning for students from upper secondary/high school level through to university first degree level. A distinctive feature of the journal is its emphasis on the applications of mathematics and mathematical modelling within the context of mathematics education world-wide. The focus of the journal is on the teaching of mathematics and all articles should relate explicitly to the teaching and learning of mathematics and its applications. The journal’s readership consists of mathematics teachers, lecturers, students, researchers and those concerned with curriculum development and assessment, indeed anyone concerned about the education of users of mathematics. Contributions are invited in two forms: Section A consists of research articles based on empirical investigation and/or theoretical argument whose conclusions inform the improvement of mathematics teaching and learning at the relevant level. Section B consists of articles based on scholarly argument, informed by knowledge of research, such as innovative approaches to teaching with a justification for considering their wider use." "Teaching Mathematics and its Applications has broadened its scope to include research on mathematics teacher education and professional development at upper secondary and university levels, recognizing the importance of mathematical knowledge for effective teaching." | G153: https://www.google.com/search?q=%22Teaching+Mathematics+and+its+Applications%22+official+journal | H153: N/D | I153: 5 | J153: Consultar política atual | K153: Open Access | L153: Não informado | M153: Homepage oficial não foi confirmada; a URL fornecida é uma busca de localização. APC deve ser conferido antes da submissão. Tempo editorial não informado de forma verificável. | N153: https://docs.google.com/spreadsheets/d/1wSi_RMs07HmPMkirnmFInYvAovt0vWFP9lLaMk694Cc/htmlview/sheet?gid=0&headers=true
A154: Texas Mathematics Teacher | B154: TMT | C154: TCTM | D154: N/D | E154: matemática | F154: Prática e formação docente em matemática, recursos didáticos e desenvolvimento profissional para professores. | G154: https://www.google.com/search?q=%22Texas+Mathematics+Teacher%22+official+journal | H154: N/D | I154: 4 | J154: Consultar política atual | K154: Open Access | L154: Não informado | M154: Homepage oficial não foi confirmada; a URL fornecida é uma busca de localização. APC deve ser conferido antes da submissão. Tempo editorial não informado de forma verificável. | N154: https://docs.google.com/spreadsheets/d/1wSi_RMs07HmPMkirnmFInYvAovt0vWFP9lLaMk694Cc/htmlview/sheet?gid=0&headers=true
A155: The American Mathematical Monthly | B155: AMM | C155: Taylor & Francis | D155: 0.4 | E155: matemática | F155: The American Mathematical Monthly publishes articles, notes, and other features about mathematics and the profession. Its readers span a broad spectrum of mathematical interests and abilities. Authors are invited to submit articles and notes that bring interesting mathematical ideas to a wide audience of Monthly readers. | G155: https://www.tandfonline.com/journals/uamm20 | H155: https://doi.org/10.1080/00029890.2020.1793635 | I155: 5 | J155: Consultar política atual | K155: Híbrido/consultar | L155: Não informado | M155: APC deve ser conferido antes da submissão. Tempo editorial não informado de forma verificável. | N155: https://docs.google.com/spreadsheets/d/1wSi_RMs07HmPMkirnmFInYvAovt0vWFP9lLaMk694Cc/htmlview/sheet?gid=0&headers=true
A156: The College Mathematics Journal | B156: TCMJ | C156: Taylor & Francis | D156: 0.45 | E156: matemática | F156: The College Mathematics Journal is designed to enhance classroom learning and stimulate thinking regarding undergraduate mathematics. It publishes research articles, short classroom capsules, problems and solutions, media reviews, and other pieces. All are aimed at the college mathematics curriculum with emphasis on topics taught in the first two years. | G156: https://www.tandfonline.com/journals/ucmj20 | H156: https://www.tandfonline.com/doi/full/10.1080/07468342.2026.2661551 | I156: 5 | J156: Consultar política atual | K156: Híbrido/consultar | L156: Não informado | M156: APC deve ser conferido antes da submissão. Tempo editorial não informado de forma verificável. | N156: https://docs.google.com/spreadsheets/d/1wSi_RMs07HmPMkirnmFInYvAovt0vWFP9lLaMk694Cc/htmlview/sheet?gid=0&headers=true
A157: The Mathematical Intelligencer | B157: TMI | C157: Springer Nature Link | D157: 0.4 | E157: matemática | F157: The Mathematical Intelligencer publishes articles about mathematics, about mathematicians, and about the history and culture of mathematics. Written in an engaging, informal style,* our pages inform and entertain a broad audience of mathematicians and the wider intellectual community. We welcome expository articles on all kinds of mathematics, and articles that portray the diversity of mathematical communities and mathematical thought, emergent mathematical communities around the world, new interdisciplinary trends, and relations between mathematics and other areas of culture. Humor is welcome, as are puzzles, poetry, fiction, and art. *Note: The traditional Definition/Theorem/Proof style of research articles is not appropriate here, nor are articles aimed only at specialists. | G157: https://link.springer.com/journal/283 | H157: https://doi.org/10.1007/s00283-014-9525-6 | I157: 5 | J157: Consultar política atual | K157: Híbrido/consultar | L157: Não informado | M157: APC deve ser conferido antes da submissão. Tempo editorial não informado de forma verificável. | N157: https://docs.google.com/spreadsheets/d/1wSi_RMs07HmPMkirnmFInYvAovt0vWFP9lLaMk694Cc/htmlview/sheet?gid=0&headers=true
A158: The Mathematics Educator | B158: ME | C158: MESA in the Department of Mathematics and Science Education at the University of Georgia | D158: N/D | E158: matemática | F158: a student-produced journal published semiannually by the Mathematics Education Student Association (MESA) in the Department of Mathematics and Science Education at the University of Georgia. reports of research (including experiments, case studies, surveys, and historical studies) descriptions of curriclum projects or classroom experiences, literature reviews, theoretical analyses, critiques of general articles, research reports, books, or software commentaries on research methods in mathematics education, commentaries on public policies in mathematics education. | G158: https://www.google.com/search?q=%22The+Mathematics+Educator%22+official+journal | H158: N/D | I158: 4 | J158: Consultar política atual | K158: Open Access | L158: ≈6–8 meses | M158: Homepage oficial não foi confirmada; a URL fornecida é uma busca de localização. APC deve ser conferido antes da submissão. | N158: https://docs.google.com/spreadsheets/d/1wSi_RMs07HmPMkirnmFInYvAovt0vWFP9lLaMk694Cc/htmlview/sheet?gid=0&headers=true
A159: The Mathematics Enthusiast | B159: ME | C159: Information Age Publishing | D159: N/D | E159: matemática | F159: Former title: The Montana Mathematics Enthusiast This journal "is an eclectic internationally circulated peer reviewed journal which focuses on mathematics content, mathematics education research, innovation, interdisciplinary issues and pedagogy... Articles appearing in the journal address issues related to mathematical thinking, teaching and learning at all levels. The focus includes specific mathematics content and advances in that area accessible to readers, as well as political, social and cultural issues related to mathematics education. Journal articles cover a wide spectrum of topics such as mathematics content (including advanced mathematics), educational studies related to mathematics, and reports of innovative pedagogical practices with the hope of stimulating dialogue between pre-service and practicing teachers, university educators and mathematicians. The journal is interested in research based articles as well as historical, philosophical, political, cross-cultural and systems perspectives on mathematics content, its teaching and learning." Affiliations: ScholarWorks University of Montana | G159: https://www.google.com/search?q=%22The+Mathematics+Enthusiast%22+official+journal | H159: N/D | I159: 4 | J159: Consultar política atual | K159: Não confirmado | L159: ≈8–12 meses | M159: Homepage oficial não foi confirmada; a URL fornecida é uma busca de localização. APC deve ser conferido antes da submissão. | N159: https://docs.google.com/spreadsheets/d/1wSi_RMs07HmPMkirnmFInYvAovt0vWFP9lLaMk694Cc/htmlview/sheet?gid=0&headers=true
A160: The Oregon Mathematics Teacher | B160: TOMT | C160: Oregon Council of Teachers of Mathematics | D160: N/D | E160: matemática | F160: "TOMT includes information about activities of OCTM and publishes teacher articles and student activities for grades K through 14 and for teacher-education colleges." | G160: https://www.google.com/search?q=%22The+Oregon+Mathematics+Teacher%22+official+journal | H160: N/D | I160: 4 | J160: Consultar política atual | K160: Não confirmado | L160: Não informado | M160: Homepage oficial não foi confirmada; a URL fornecida é uma busca de localização. APC deve ser conferido antes da submissão. Tempo editorial não informado de forma verificável. | N160: https://docs.google.com/spreadsheets/d/1wSi_RMs07HmPMkirnmFInYvAovt0vWFP9lLaMk694Cc/htmlview/sheet?gid=0&headers=true
A161: The Teaching of Mathematics | B161: TTM | C161: Društvo matematičara Srbije, Beograd (Mathematical Society of Serbia) | D161: N/D | E161: matemática | F161: 'THE TEACHING OF MATHEMATICS started in 1998 as a separate volume of Nastava Matematike, a pedagogical journal in Serbian, which has been edited since 1952. The Teaching is exclusively research oriented. All contributed papers containing essentially new ideas and techniques relevant for teaching of mathematics at all levels, recommended by our referees, will be considered for publication. In particular, the papers containing subject analysis of selected teaching themas and new ways of their modelling will be welcomed. The languages of this Journal are the congress languages of the International Mathematical Union. This journal approves and supports the International Mathematical Union's Best Current Practices for Journals (2010) and Code of Practice (2012) by European Mathematical Society Ethics Committee. The Teaching of Mathematics journal does not have any article processing charges (APCs) nor article submission charges nor publication fee.'' | G161: https://www.google.com/search?q=%22The+Teaching+of+Mathematics%22+official+journal | H161: N/D | I161: 3 | J161: Sem APC | K161: Open Access | L161: Não informado | M161: Homepage oficial não foi confirmada; a URL fornecida é uma busca de localização. Tempo editorial não informado de forma verificável. | N161: https://docs.google.com/spreadsheets/d/1wSi_RMs07HmPMkirnmFInYvAovt0vWFP9lLaMk694Cc/htmlview/sheet?gid=0&headers=true
A162: Theory into Practice | B162: TP | C162: Routledge and Ohio State University. | D162: 1.9 | E162: matemática | F162: Each issue typically has a central theme developed by a guest editor. The guest editor submits a proposal to have an issue around a particular theme (typically 8-10 articles per issue). Then, upon approval, the guest editor solicits the articles from authors. "Authors should be made aware that TIP articles focus on concepts and ideas. Although authors are encouraged to include research and case studies to support ideas, an article should not focus on a single research study or case example. Manuscripts are generally 3,000-4,000 words in length." | G162: https://www.google.com/search?q=%22Theory+into+Practice%22+official+journal | H162: N/D | I162: 3 | J162: Consultar política atual | K162: Híbrido | L162: Não informado | M162: Homepage oficial não foi confirmada; a URL fornecida é uma busca de localização. APC deve ser conferido antes da submissão. Tempo editorial não informado de forma verificável. | N162: https://docs.google.com/spreadsheets/d/1wSi_RMs07HmPMkirnmFInYvAovt0vWFP9lLaMk694Cc/htmlview/sheet?gid=0&headers=true
A163: Turkish Journal of Computer and Mathematics Education | B163: TURCOMAT | C163: Science Research Society | D163: N/D | E163: matemática | F163: 'Turkish Journal of Computer and Mathematics Education (TURCOMAT) is an international refereed (peer-reviewed) journal and published three issues per year (April, August and December). The Journal publishes educational researches related to mathematics education (See focus and scope on website). The journal is devoted to action researcher mathematics teachers, teacher educators, researchers, computer education and mathematics teacher candidates, foundations and people who are interested in mathematics education.'' | G163: https://www.google.com/search?q=%22Turkish+Journal+of+Computer+and+Mathematics+Education%22+official+journal | H163: N/D | I163: 4 | J163: Consultar política atual | K163: Open Access | L163: Não informado | M163: Homepage oficial não foi confirmada; a URL fornecida é uma busca de localização. APC deve ser conferido antes da submissão. Tempo editorial não informado de forma verificável. | N163: https://docs.google.com/spreadsheets/d/1wSi_RMs07HmPMkirnmFInYvAovt0vWFP9lLaMk694Cc/htmlview/sheet?gid=0&headers=true
A164: Turkish Journal of Mathematics Education | B164: TUJME | C164: TURKBILMAT Education Services | D164: N/D | E164: matemática | F164: "The Journal publishes educational researches related to mathematics education. The journal is devoted to action researcher mathematics teachers, teacher educators, researchers, mathematics teacher candidates, foundations, and people who are interested in mathematics education." | G164: https://tujme.org/index.php/tujme/index | H164: N/D | I164: 4 | J164: Consultar política atual | K164: Open Access | L164: Não informado | M164: APC deve ser conferido antes da submissão. Tempo editorial não informado de forma verificável. | N164: https://docs.google.com/spreadsheets/d/1wSi_RMs07HmPMkirnmFInYvAovt0vWFP9lLaMk694Cc/htmlview/sheet?gid=0&headers=true
A165: Unnes Journal of Mathematics Education | B165: UJME | C165: Department of Mathematics, Faculty of Mathematics and Natural Sciences, Universitas Negeri Semarang | D165: N/D | E165: matemática | F165: 'Unnes Journal of Mathematics Education (UJME) publishes research issues on mathematics education. The UJME processes manuscripts resulted from a research in mathematics education scope, which includes, but is not limited to the topics of didactic development research (DDR), research and development (RnD) in mathematics education, ethnomathematics in mathematics education, realistic mathematics education, psychology of mathematics education and technology in mathematical instruction. The manuscript must be original research, written in English, and not be simultaneously submitted to another journal or conference.'' | G165: https://www.google.com/search?q=%22Unnes+Journal+of+Mathematics+Education%22+official+journal | H165: N/D | I165: 4 | J165: Consultar política atual | K165: Open Access | L165: Não informado | M165: Homepage oficial não foi confirmada; a URL fornecida é uma busca de localização. APC deve ser conferido antes da submissão. Tempo editorial não informado de forma verificável. | N165: https://docs.google.com/spreadsheets/d/1wSi_RMs07HmPMkirnmFInYvAovt0vWFP9lLaMk694Cc/htmlview/sheet?gid=0&headers=true
A166: Virginia Mathematics Teacher | B166: VMT | C166: Virginia Council of Teachers of Mathematics (affiliate of NCTM) | D166: N/D | E166: matemática | F166: "We gladly accept articles of interest to our membership on a rolling basis. All articles should be a blinded, single-spaced Word document with 12 pt. Times New Roman font, in APA style. To submit an article, click the "Submit via Scholastica" button below. To get more information, contact Dr. Agida Manizade at vmt@radford.edu. Virginia residents whose articles appear in the VMT will be granted free membership for one year." | G166: https://www.google.com/search?q=%22Virginia+Mathematics+Teacher%22+official+journal | H166: N/D | I166: 4 | J166: Consultar política atual | K166: Membros | L166: Não informado | M166: Homepage oficial não foi confirmada; a URL fornecida é uma busca de localização. APC deve ser conferido antes da submissão. Tempo editorial não informado de forma verificável. | N166: https://docs.google.com/spreadsheets/d/1wSi_RMs07HmPMkirnmFInYvAovt0vWFP9lLaMk694Cc/htmlview/sheet?gid=0&headers=true
A167: World Journal of Education | B167: WJE | C167: Sciedu Press (Canada) | D167: N/D | E167: matemática | F167: "World Journal of Education is a peer-review journal, published by Sciedu Press. It is devoted to publishing research papers in the fields of education, teaching, learning and other relevant subjects. This includes primary, secondary, tertiary and other higher education disciplines such as but not limited to special education (SpEd), normal and even express streams of the academe. It is published semi-annually in both online and printed versions." | G167: https://www.google.com/search?q=%22World+Journal+of+Education%22+official+journal | H167: N/D | I167: 3 | J167: Consultar política atual | K167: Não confirmado | L167: Não informado | M167: Homepage oficial não foi confirmada; a URL fornecida é uma busca de localização. APC deve ser conferido antes da submissão. Tempo editorial não informado de forma verificável. | N167: https://docs.google.com/spreadsheets/d/1wSi_RMs07HmPMkirnmFInYvAovt0vWFP9lLaMk694Cc/htmlview/sheet?gid=0&headers=true
A168: ZDM - Mathematics Education | B168: ZDM | C168: Springer | D168: 3.104 | E168: matemática | F168: "ZDM is one of the oldest mathematics education research journals in publication. The journal surveys, discusses, and builds upon current research and theoretical-based perspectives in mathematics education. In addition, it serves as a forum for critical analysis of issues within the field. All the papers published in the journal’s six annual themed issues are strictly by invitation. These papers are subject to an internal peer review by selected members from the editorial board as well as an external review by invited experts. The journal targets readers from around the world in mathematics education research who are interested in current developments in the field." | G168: https://www.google.com/search?q=%22ZDM+-+Mathematics+Education%22+official+journal | H168: N/D | I168: 4 | J168: Consultar política atual | K168: Open Access | L168: ≈81 dias | M168: Homepage oficial não foi confirmada; a URL fornecida é uma busca de localização. APC deve ser conferido antes da submissão. | N168: https://docs.google.com/spreadsheets/d/1wSi_RMs07HmPMkirnmFInYvAovt0vWFP9lLaMk694Cc/htmlview/sheet?gid=0&headers=true
